Workbook

Sheet 1001 OK
B1: 1001 | C1: Pagos o abonos en cuenta y retenciones practicadas V10
N2: 169 Colombia | O2: VALOR DE LA COMPRA DESCONTADO NOTA CREDITO
B3: Concepto | C3: Tipo de documento | D3: Número identificación del informado | E3: tipo | F3: Primer apellido del informado | G3: Segundo apellido del informado | H3: Primer nombre del informado | I3: Otros nombres del informado | J3: Razón social informado | K3: Dirección | L3: Código dpto. | M3: Código mcp | N3: País de residencia o domicilio | O3: Pago o abono en cuenta deducible | Q3: Pago o abono en cuenta NO deducible | R3: Iva mayor valor del costo o gasto deducible | S3: Iva mayor valor del costo o gasto no deducible | U3: Retención en la fuente practicada renta | V3: Retención en la fuente practicada IVA régimen común | W3: Retención en la fuente practicada IVA no domiciliados
A4: 1 | B4: 5007 | C4: 31 | D4: 805011074 | E4: 31 | J4: ADIDAS COLOMBIA LTDA | N4: 169 | O4: 2823025 | P4: 0 | Q4: 0 | R4: 0 | S4: 0 | T4: 0 | U4: 0 | V4: 0 | W4: 0
A5: 2 | B5: 5007 | C5: 31 | D5: 900128596 | E5: #N/A | F5: #N/A | G5: #N/A | H5: #N/A | I5: #N/A | J5: AGRO PEREZ S.A.S | K5: #N/A | L5: #N/A | M5: #N/A | N5: 169 | O5: 686030 | P5: 0 | Q5: 0 | R5: 0 | S5: 0 | T5: 0 | U5: 0 | V5: 0 | W5: 0
A6: 3 | B6: 5007 | C6: 31 | D6: 901073241 | E6: 31 | J6: AGROTECNICO J.O. SAS - BULERIAS | K6: CRA 7 N 5-55 | N6: 169 | O6: 263561 | P6: 0 | Q6: 0 | R6: 0 | S6: 0 | T6: 0 | U6: 0 | V6: 0 | W6: 0
A7: 4 | B7: 5007 | C7: 31 | D7: 860013771 | E7: 31 | J7: AJOVER DARNEL S.A.S. | K7: TRANSVERSAL 93 N° 65A-30 | N7: 169 | O7: 13702300 | P7: 0 | Q7: 0 | R7: 0 | S7: 0 | T7: 0 | U7: 0 | V7: 0 | W7: 0
A8: 5 | B8: 5007 | C8: 13 | D8: 13720777 | E8: #N/A | F8: #N/A | G8: #N/A | H8: #N/A | I8: #N/A | J8: ALEXANDER PALOMINO | K8: #N/A | L8: #N/A | M8: #N/A | N8: 169 | O8: 3492000 | P8: 0 | Q8: 0 | R8: 0 | S8: 0 | T8: 0 | U8: 0 | V8: 0 | W8: 0
A9: 6 | B9: 5007 | C9: 13 | D9: 1126038685 | E9: 13 | F9: EL REDA | G9: AWADA | H9: ALI | I9: RIAD | J9: ALI RIAD EL REDA AWADA | N9: 169 | O9: 16354484 | P9: 0 | Q9: 0 | R9: 0 | S9: 0 | T9: 0 | U9: 0 | V9: 0 | W9: 0
A10: 7 | B10: 5007 | C10: 31 | D10: 901368217 | E10: 31 | J10: ALIANZA MEGA GROUP S.A.S. | K10: CRA 77 C 48 B 208 PISO 2 | L10: 05 | M10: 001 | N10: 169 | O10: 1576635 | P10: 0 | Q10: 0 | R10: 0 | S10: 0 | T10: 0 | U10: 0 | V10: 0 | W10: 0
A11: 8 | B11: 5007 | C11: 31 | D11: 800160395 | E11: 31 | J11: ALMACEN Y DISTRIBUIDORA GONZALEZ S.A.S. | K11: CR 42 32 28 | L11: 08 | M11: 001 | N11: 169 | O11: 20732857 | P11: 0 | Q11: 0 | R11: 0 | S11: 0 | T11: 0 | U11: 0 | V11: 0 | W11: 0
A12: 9 | B12: 5007 | C12: 31 | D12: 901252634 | E12: #N/A | F12: #N/A | G12: #N/A | H12: #N/A | I12: #N/A | J12: Aluminios Super Golden SAS | K12: #N/A | L12: #N/A | M12: #N/A | N12: 169 | O12: 7772138 | P12: 0 | Q12: 0 | R12: 0 | S12: 0 | T12: 0 | U12: 0 | V12: 0 | W12: 0
A13: 10 | B13: 5007 | C13: 31 | D13: 13458366 | E13: #N/A | F13: #N/A | G13: #N/A | H13: #N/A | I13: #N/A | J13: ALVARO GAMBOA PRADA | K13: #N/A | L13: #N/A | M13: #N/A | N13: 169 | O13: 13055097 | P13: 0 | Q13: 0 | R13: 0 | S13: 0 | T13: 0 | U13: 0 | V13: 0 | W13: 0
A14: 11 | B14: 5007 | C14: 31 | D14: 900628277 | E14: #N/A | F14: #N/A | G14: #N/A | H14: #N/A | I14: #N/A | J14: AMERICAN APPAREL COLOMBIA SAS | K14: #N/A | L14: #N/A | M14: #N/A | N14: 169 | O14: 2570740 | P14: 0 | Q14: 0 | R14: 0 | S14: 0 | T14: 0 | U14: 0 | V14: 0 | W14: 0
A15: 12 | B15: 5007 | C15: 31 | D15: 43787151 | E15: #N/A | F15: #N/A | G15: #N/A | H15: #N/A | I15: #N/A | J15: ANA MARIA GALLEGO QUINTERO | K15: #N/A | L15: #N/A | M15: #N/A | N15: 169 | O15: 2621880 | P15: 0 | Q15: 0 | R15: 0 | S15: 0 | T15: 0 | U15: 0 | V15: 0 | W15: 0
A16: 13 | B16: 5007 | C16: 31 | D16: 57300574 | E16: 13 | F16: LOZADA | G16: DE PLATA | H16: ANA | I16: PAULINA | J16: ANA PAULINA LOZADA DE PLATA | N16: 169 | O16: 11397059 | P16: 0 | Q16: 0 | R16: 0 | S16: 0 | T16: 0 | U16: 0 | V16: 0 | W16: 0
A17: 14 | B17: 5007 | C17: 31 | D17: 39432192 | E17: #N/A | F17: #N/A | G17: #N/A | H17: #N/A | I17: #N/A | J17: ANGELA MARIA OTALVARO OROZCO | K17: #N/A | L17: #N/A | M17: #N/A | N17: 169 | O17: 120900 | P17: 0 | Q17: 0 | R17: 0 | S17: 0 | T17: 0 | U17: 0 | V17: 0 | W17: 0
A18: 15 | B18: 5007 | C18: 31 | D18: 860002184 | E18: 31 | J18: AXA COLPATRIA SEGUROS S.A. | N18: 169 | O18: 1063300 | P18: 0 | Q18: 0 | R18: 0 | S18: 0 | T18: 0 | U18: 0 | V18: 0 | W18: 0
A19: 16 | B19: 5007 | C19: 31 | D19: 860000135 | E19: 31 | J19: AZUL K S.A.S. | K19: AUT SUR 60 51 | L19: 11 | M19: 001 | N19: 169 | O19: 13066903 | P19: 0 | Q19: 0 | R19: 0 | S19: 0 | T19: 0 | U19: 0 | V19: 0 | W19: 0
A20: 17 | B20: 5007 | C20: 31 | D20: 1037973102 | E20: 13 | F20: MARIN | G20: DUQUE | H20: BAIRON | J20: BAIRON MARIN DUQUE | N20: 169 | O20: 228500 | P20: 0 | Q20: 0 | R20: 0 | S20: 0 | T20: 0 | U20: 0 | V20: 0 | W20: 0
A21: 18 | B21: 5007 | C21: 31 | D21: 811013231 | E21: #N/A | F21: #N/A | G21: #N/A | H21: #N/A | I21: #N/A | J21: BAZAR DE LA CONSTRUCCION SAS | K21: #N/A | L21: #N/A | M21: #N/A | N21: 169 | O21: 25853411 | P21: 0 | Q21: 0 | R21: 0 | S21: 0 | T21: 0 | U21: 0 | V21: 0 | W21: 0
A22: 19 | B22: 5007 | C22: 31 | D22: 900615349 | E22: 31 | J22: BELLPROF GROUP S.A.S | K22: CALLE 34 N. 43-22 | N22: 169 | O22: 1979654 | P22: 0 | Q22: 0 | R22: 0 | S22: 0 | T22: 0 | U22: 0 | V22: 0 | W22: 0
A23: 20 | B23: 5007 | C23: 31 | D23: 88220927 | E23: 13 | F23: BERMON | G23: CAÑAS | H23: WALTER | I23: ALDEMAR | J23: BERMON CAÑAS WALTER ALDEMAR | K23: CALLE 2 N 5 03 | N23: 169 | O23: 1974790 | P23: 0 | Q23: 0 | R23: 0 | S23: 0 | T23: 0 | U23: 0 | V23: 0 | W23: 0
A24: 21 | B24: 5007 | C24: 31 | D24: 901523051 | E24: #N/A | F24: #N/A | G24: #N/A | H24: #N/A | I24: #N/A | J24: BOMBOFIESTAS SAS | K24: #N/A | L24: #N/A | M24: #N/A | N24: 169 | O24: 334353 | P24: 0 | Q24: 0 | R24: 0 | S24: 0 | T24: 0 | U24: 0 | V24: 0 | W24: 0
A25: 22 | B25: 5007 | C25: 31 | D25: 800066618 | E25: 31 | J25: BRAZZA SPORT S.A.S | K25: CR 56B 49A 29 PISO 15 | N25: 169 | O25: 3983912 | P25: 0 | Q25: 0 | R25: 0 | S25: 0 | T25: 0 | U25: 0 | V25: 0 | W25: 0
A26: 23 | B26: 5007 | C26: 31 | D26: 900586774 | E26: 31 | J26: BRIO IN SAS | K26: CALLE 4 - 14 05 | N26: 169 | O26: 31348224 | P26: 0 | Q26: 0 | R26: 0 | S26: 0 | T26: 0 | U26: 0 | V26: 0 | W26: 0
A27: 24 | B27: 5007 | C27: 31 | D27: 890924167 | E27: 31 | J27: C.I HERMECO S.A | K27: CALLE 49 A N° 55 A-45 INT 1105 | N27: 169 | O27: 1086873 | P27: 0 | Q27: 0 | R27: 0 | S27: 0 | T27: 0 | U27: 0 | V27: 0 | W27: 0
A28: 25 | B28: 5007 | C28: 31 | D28: 901352891 | E28: 31 | J28: CACHARRERIA LOS MARINILLOS DE LA COSTA SAS | K28: CRA 41 N 29 30 BARRANQUILLA | N28: 169 | O28: 47644588 | P28: 0 | Q28: 0 | R28: 0 | S28: 0 | T28: 0 | U28: 0 | V28: 0 | W28: 0
A29: 26 | B29: 5007 | C29: 31 | D29: 901504764 | E29: 31 | J29: CALIFORNIA CTG SAS | K29: CC E INDUSTRIAL TERNERA 1 BODEGA 50 | N29: 169 | O29: 844800 | P29: 0 | Q29: 0 | R29: 0 | S29: 0 | T29: 0 | U29: 0 | V29: 0 | W29: 0
A30: 27 | B30: 5007 | C30: 31 | D30: 32755147 | E30: 13 | F30: LILIANA | G30: MARIA | H30: CANTILLO | I30: PLATA | J30: CANTILLO PLATA LILIANA MARIA | K30: CLE 31 N 40 53 PISO 2 | N30: 169 | O30: 11747534 | P30: 0 | Q30: 0 | R30: 0 | S30: 0 | T30: 0 | U30: 0 | V30: 0 | W30: 0
A31: 28 | B31: 5007 | C31: 31 | D31: 901778121 | E31: 31 | J31: CARIBE S.A.S | K31: CL 34 43 156P 3 BG B 05 | N31: 169 | O31: 649700 | P31: 0 | Q31: 0 | R31: 0 | S31: 0 | T31: 0 | U31: 0 | V31: 0 | W31: 0
A32: 29 | B32: 5007 | C32: 31 | D32: 901358015 | E32: 31 | J32: CASA DEL TEJIDO S.A.S | N32: 169 | O32: 3967895 | P32: 0 | Q32: 0 | R32: 0 | S32: 0 | T32: 0 | U32: 0 | V32: 0 | W32: 0
A33: 30 | B33: 5007 | C33: 31 | D33: 800221591 | E33: #N/A | F33: #N/A | G33: #N/A | H33: #N/A | I33: #N/A | J33: CENTRO ACEROS DEL CARIBE LTDA | K33: #N/A | L33: #N/A | M33: #N/A | N33: 169 | O33: 9315189 | P33: 0 | Q33: 0 | R33: 0 | S33: 0 | T33: 0 | U33: 0 | V33: 0 | W33: 0
A34: 31 | B34: 5007 | C34: 31 | D34: 900158685 | E34: 31 | J34: CENTURY SPORTS SAS | N34: 169 | O34: 575588 | P34: 0 | Q34: 0 | R34: 0 | S34: 0 | T34: 0 | U34: 0 | V34: 0 | W34: 0
A35: 32 | B35: 5007 | C35: 31 | D35: 901151055 | E35: #N/A | F35: #N/A | G35: #N/A | H35: #N/A | I35: #N/A | J35: CERVEH S.A.S. | K35: #N/A | L35: #N/A | M35: #N/A | N35: 169 | O35: 277092 | P35: 0 | Q35: 0 | R35: 0 | S35: 0 | T35: 0 | U35: 0 | V35: 0 | W35: 0
A36: 33 | B36: 5007 | C36: 31 | D36: 901265547 | E36: 31 | J36: CES RED LOGISTICA S.A.S | N36: 169 | O36: 42500 | P36: 0 | Q36: 0 | R36: 0 | S36: 0 | T36: 0 | U36: 0 | V36: 0 | W36: 0
A37: 34 | B37: 5007 | C37: 31 | D37: 15446723 | E37: 13 | F37: BEDOYA | G37: CORRALES | H37: JUAN | I37: DAVID | J37: CICLOORBE BICICLETAS Y TIENDA DEPORTIVA | N37: 169 | O37: 203277 | P37: 0 | Q37: 0 | R37: 0 | S37: 0 | T37: 0 | U37: 0 | V37: 0 | W37: 0
A38: 35 | B38: 5007 | C38: 31 | D38: 900816838 | E38: 31 | J38: CMX S.A.S. | N38: 169 | O38: 84874 | P38: 0 | Q38: 0 | R38: 0 | S38: 0 | T38: 0 | U38: 0 | V38: 0 | W38: 0
A39: 36 | B39: 5007 | C39: 31 | D39: 901422631 | E39: 31 | J39: COLBALONES ZZ 2020 S.A.S 01 00 | K39: CL 37 45 87 | L39: 08 | M39: 001 | N39: 169 | O39: 14532773 | P39: 0 | Q39: 0 | R39: 0 | S39: 0 | T39: 0 | U39: 0 | V39: 0 | W39: 0
A40: 37 | B40: 5007 | C40: 31 | D40: 890900943 | E40: 31 | J40: COLOMBIANA DE COMERCIO S.A. | K40: GRAN ABASTO BG 11 LC 1 | L40: 11 | M40: 001 | N40: 169 | O40: 2185448 | P40: 0 | Q40: 0 | R40: 0 | S40: 0 | T40: 0 | U40: 0 | V40: 0 | W40: 0
A41: 38 | B41: 5007 | C41: 31 | D41: 811027885 | E41: 31 | J41: COLPLAST S.A.S | K41: CRA 48 98A SUR 230 | N41: 169 | O41: 76919012 | P41: 0 | Q41: 0 | R41: 0 | S41: 0 | T41: 0 | U41: 0 | V41: 0 | W41: 0
A42: 39 | B42: 5007 | C42: 31 | D42: 800185306 | E42: 31 | J42: COLVANES S.A.S | N42: 169 | O42: 136428 | P42: 0 | Q42: 0 | R42: 0 | S42: 0 | T42: 0 | U42: 0 | V42: 0 | W42: 0
A43: 40 | B43: 5007 | C43: 31 | D43: 811006439 | E43: 31 | J43: COMERCIAL LEONIDAS SAS | N43: 169 | O43: 137731 | P43: 0 | Q43: 0 | R43: 0 | S43: 0 | T43: 0 | U43: 0 | V43: 0 | W43: 0
A44: 41 | B44: 5007 | C44: 31 | D44: 900342297 | E44: 31 | J44: COMERCIALIZADORA ARTURO CALLE S.A.S | N44: 169 | O44: 125042 | P44: 0 | Q44: 0 | R44: 0 | S44: 0 | T44: 0 | U44: 0 | V44: 0 | W44: 0
A45: 42 | B45: 5007 | C45: 31 | D45: 900461291 | E45: #N/A | F45: #N/A | G45: #N/A | H45: #N/A | I45: #N/A | J45: COMERCIALIZADORA CHALIS S.A.S. | K45: #N/A | L45: #N/A | M45: #N/A | N45: 169 | O45: 587899 | P45: 0 | Q45: 0 | R45: 0 | S45: 0 | T45: 0 | U45: 0 | V45: 0 | W45: 0
A46: 43 | B46: 5007 | C46: 31 | D46: 900670914 | E46: 31 | J46: COMERCIALIZADORA ESCOBAR ORTIZ S.A.S. | K46: CR 32 4D 140 BG 1 | L46: 08 | M46: 296 | N46: 169 | O46: 3273138 | P46: 0 | Q46: 0 | R46: 0 | S46: 0 | T46: 0 | U46: 0 | V46: 0 | W46: 0
A47: 44 | B47: 5007 | C47: 31 | D47: 901938748 | E47: #N/A | F47: #N/A | G47: #N/A | H47: #N/A | I47: #N/A | J47: COMERCIALIZADORA KAMARANDRES S.A.S | K47: #N/A | L47: #N/A | M47: #N/A | N47: 169 | O47: 1678800 | P47: 0 | Q47: 0 | R47: 0 | S47: 0 | T47: 0 | U47: 0 | V47: 0 | W47: 0
A48: 45 | B48: 5007 | C48: 31 | D48: 900436082 | E48: 31 | J48: COMERCIALIZADORA LISEB S.A.S. | K48: CALLE 31 N. 40-53 PISO 2 | N48: 169 | O48: 1455126 | P48: 0 | Q48: 0 | R48: 0 | S48: 0 | T48: 0 | U48: 0 | V48: 0 | W48: 0
A49: 46 | B49: 5007 | C49: 31 | D49: 900482118 | E49: 31 | J49: COMERCIALIZADORA LYON SAS | K49: CAR 10 N 10 83 PISO 4 BG 10 Y 11 | N49: 169 | O49: 9347004 | P49: 0 | Q49: 0 | R49: 0 | S49: 0 | T49: 0 | U49: 0 | V49: 0 | W49: 0
A50: 47 | B50: 5007 | C50: 31 | D50: 901724166 | E50: 31 | J50: COMERCIALIZADORA SAN JOSE MG SAS | K50: CL 32 44 75 | L50: 08 | M50: 001 | N50: 169 | O50: 3985541 | P50: 0 | Q50: 0 | R50: 0 | S50: 0 | T50: 0 | U50: 0 | V50: 0 | W50: 0
A51: 48 | B51: 5007 | C51: 31 | D51: 900990570 | E51: 31 | J51: COMERCIALIZADORA SAYARA S.A.S | N51: 169 | O51: 411513 | P51: 0 | Q51: 0 | R51: 0 | S51: 0 | T51: 0 | U51: 0 | V51: 0 | W51: 0
A52: 49 | B52: 5007 | C52: 31 | D52: 901661391 | E52: 31 | J52: COMERCIALIZADORA SOL DE ORIENTE MG SAS | K52: CALLE 34 43-70 LOC 151 | N52: 169 | O52: 5589153 | P52: 0 | Q52: 0 | R52: 0 | S52: 0 | T52: 0 | U52: 0 | V52: 0 | W52: 0
A53: 50 | B53: 5007 | C53: 31 | D53: 901673847 | E53: 31 | J53: COMERCIALIZADORA VALMORE SAS | K53: CALLE 34 43-156 PISO 3 BOD BC 05 CC SHOP | N53: 169 | O53: 4115800 | P53: 0 | Q53: 0 | R53: 0 | S53: 0 | T53: 0 | U53: 0 | V53: 0 | W53: 0
A54: 51 | B54: 5007 | C54: 31 | D54: 1098703608 | E54: #N/A | F54: #N/A | G54: #N/A | H54: #N/A | I54: #N/A | J54: CONFECCIONES MY LADY | K54: #N/A | L54: #N/A | M54: #N/A | N54: 169 | O54: 2248740 | P54: 0 | Q54: 0 | R54: 0 | S54: 0 | T54: 0 | U54: 0 | V54: 0 | W54: 0
A55: 52 | B55: 5007 | C55: 31 | D55: 901160142 | E55: #N/A | F55: #N/A | G55: #N/A | H55: #N/A | I55: #N/A | J55: CONFECCIONES YESHUA SHAMMAH S.A.S | K55: #N/A | L55: #N/A | M55: #N/A | N55: 169 | O55: 12992000 | P55: 0 | Q55: 0 | R55: 0 | S55: 0 | T55: 0 | U55: 0 | V55: 0 | W55: 0
A56: 53 | B56: 5007 | C56: 31 | D56: 890904478 | E56: 31 | J56: COOPERATIVA COLANTA | K56: CL 74 64A 51 | L56: 05 | M56: 001 | N56: 169 | O56: 3953181 | P56: 0 | Q56: 0 | R56: 0 | S56: 0 | T56: 0 | U56: 0 | V56: 0 | W56: 0
A57: 54 | B57: 5007 | C57: 31 | D57: 830011670 | E57: 31 | J57: COOPERATIVA MULTIACTIVA DE SERVICIOS SOLIDARIOS | N57: 169 | O57: 229501 | P57: 0 | Q57: 0 | R57: 0 | S57: 0 | T57: 0 | U57: 0 | V57: 0 | W57: 0
A58: 55 | B58: 5007 | C58: 31 | D58: 900144157 | E58: 31 | J58: CORDELES Y EXTRUIDOS DE COLOMBIA SOCIEDAD PORACCIONES SIMPLIFICADA | K58: CALLE 110 N6Q- 522 BG 1 BARRANQUILLA | N58: 169 | O58: 8064341 | P58: 0 | Q58: 0 | R58: 0 | S58: 0 | T58: 0 | U58: 0 | V58: 0 | W58: 0
A59: 56 | B59: 5007 | C59: 31 | D59: 816007367 | E59: 31 | J59: CREACIONES J.A S.A.S. | K59: CL 43 CR 2 | L59: 66 | M59: 170 | N59: 169 | O59: 10357298 | P59: 0 | Q59: 0 | R59: 0 | S59: 0 | T59: 0 | U59: 0 | V59: 0 | W59: 0
A60: 57 | B60: 5007 | C60: 31 | D60: 901244244 | E60: #N/A | F60: #N/A | G60: #N/A | H60: #N/A | I60: #N/A | J60: CREACIONES RUFFOS SAS | K60: #N/A | L60: #N/A | M60: #N/A | N60: 169 | O60: 4310757 | P60: 0 | Q60: 0 | R60: 0 | S60: 0 | T60: 0 | U60: 0 | V60: 0 | W60: 0
A61: 58 | B61: 5007 | C61: 31 | D61: 900264976 | E61: 31 | J61: CROCKER VIA 3 LIMITADA | K61: CR 52 29A 111 | L61: 05 | M61: 001 | N61: 169 | O61: 1810053 | P61: 0 | Q61: 0 | R61: 0 | S61: 0 | T61: 0 | U61: 0 | V61: 0 | W61: 0
A62: 59 | B62: 5007 | C62: 31 | D62: 890901672 | E62: 31 | J62: CRYSTAL S.A.S. | N62: 169 | O62: 739869 | P62: 0 | Q62: 0 | R62: 0 | S62: 0 | T62: 0 | U62: 0 | V62: 0 | W62: 0
A63: 60 | B63: 5007 | C63: 31 | D63: 800191700 | E63: 31 | J63: Cueros Vélez S.A.S. | N63: 169 | O63: 308613 | P63: 0 | Q63: 0 | R63: 0 | S63: 0 | T63: 0 | U63: 0 | V63: 0 | W63: 0
A64: 61 | B64: 5007 | C64: 31 | D64: 900428225 | E64: 31 | J64: CURE PEREIRA & CIA JUAN CUPER S. EN C. | N64: 169 | O64: 917440 | P64: 0 | Q64: 0 | R64: 0 | S64: 0 | T64: 0 | U64: 0 | V64: 0 | W64: 0
A65: 62 | B65: 5007 | C65: 31 | D65: 1098825933 | E65: #N/A | F65: #N/A | G65: #N/A | H65: #N/A | I65: #N/A | J65: DANIEL SCHNEYDER PLATA GARCIA | K65: #N/A | L65: #N/A | M65: #N/A | N65: 169 | O65: 794000 | P65: 0 | Q65: 0 | R65: 0 | S65: 0 | T65: 0 | U65: 0 | V65: 0 | W65: 0
A66: 63 | B66: 5007 | C66: 31 | D66: 900550669 | E66: #N/A | F66: #N/A | G66: #N/A | H66: #N/A | I66: #N/A | J66: DECORAESTILO J MAS F S.A.S. | K66: #N/A | L66: #N/A | M66: #N/A | N66: 169 | O66: 1949496 | P66: 0 | Q66: 0 | R66: 0 | S66: 0 | T66: 0 | U66: 0 | V66: 0 | W66: 0
A67: 64 | B67: 5007 | C67: 31 | D67: 802014196 | E67: 31 | J67: DIGABE DEL CARIBE S.A.S | N67: 169 | O67: 99400 | P67: 0 | Q67: 0 | R67: 0 | S67: 0 | T67: 0 | U67: 0 | V67: 0 | W67: 0
A68: 65 | B68: 5007 | C68: 31 | D68: 900331926 | E68: 31 | J68: DISTRIBUCIONES BAHIA REAL S.A.S | K68: CL 9A 9 28 SANTA MARTA | L68: 08 | M68: 001 | N68: 169 | O68: 29215730 | P68: 0 | Q68: 0 | R68: 0 | S68: 0 | T68: 0 | U68: 0 | V68: 0 | W68: 0
A69: 66 | B69: 5007 | C69: 31 | D69: 901216045 | E69: 31 | J69: DISTRIBUCIONES E IMPORTACIONES J.A. S.A.S | K69: CL 19 N 8 65 | L69: 66 | M69: 001 | N69: 169 | O69: 7552144 | P69: 0 | Q69: 0 | R69: 0 | S69: 0 | T69: 0 | U69: 0 | V69: 0 | W69: 0
A70: 67 | B70: 5007 | C70: 31 | D70: 802020940 | E70: 31 | J70: DISTRIBUCIONES OMAR ORREGO SA | K70: CL 33 43 134 P 2 | L70: 08 | M70: 001 | N70: 169 | O70: 106025514 | P70: 0 | Q70: 0 | R70: 0 | S70: 0 | T70: 0 | U70: 0 | V70: 0 | W70: 0
A71: 68 | B71: 5007 | C71: 31 | D71: 900026211 | E71: 31 | J71: DISTRIBUCIONES SANTA MARTA SAS | K71: CR 10 39A 36 | L71: 47 | M71: 551 | N71: 169 | O71: 65483939 | P71: 0 | Q71: 0 | R71: 0 | S71: 0 | T71: 0 | U71: 0 | V71: 0 | W71: 0
A72: 69 | B72: 5007 | C72: 31 | D72: 800081664 | E72: 31 | J72: DISTRIBUIDORA COLOMBIANA DE SENTIMIENTOS DE BELLEZA S.A.S. | N72: 169 | O72: 732647 | P72: 0 | Q72: 0 | R72: 0 | S72: 0 | T72: 0 | U72: 0 | V72: 0 | W72: 0
A73: 70 | B73: 5007 | C73: 31 | D73: 901140773 | E73: 31 | J73: DISTRIBUIDORA CRISTALERIA POPULAR S.A.S. ZOMAC | K73: CRA 30 N° 10-33 | N73: 169 | O73: 105875005 | P73: 0 | Q73: 0 | R73: 0 | S73: 0 | T73: 0 | U73: 0 | V73: 0 | W73: 0
A74: 71 | B74: 5007 | C74: 31 | D74: 901177034 | E74: 31 | J74: DISTRIBUIDORA EL REY DEL PLASTICO SAS | K74: CL 15 20 20 | L74: 76 | M74: 001 | N74: 169 | O74: 11102320
A75: 72 | B75: 5007 | C75: 31 | D75: 900431548 | E75: 31 | J75: DISTRIBUIDORA GOMEZ CONTRERAS SAS | K75: CL 32 N 42 49 | L75: 08 | M75: 001 | N75: 169 | O75: 84328317
A76: 73 | B76: 5007 | C76: 31 | D76: 800156889 | E76: 31 | J76: DISTRIBUIDORA KIRAMAR S.A.S. | K76: DG 51 31 120 | L76: 08 | M76: 758 | N76: 169 | O76: 62246604
A77: 74 | B77: 5007 | C77: 31 | D77: 70164742 | E77: 13 | F77: RAMIREZ | G77: LOAIZA | H77: JHON | I77: JAVIER | J77: DISTRIBUIDORA PUNTO MODA | N77: 169 | O77: 15011966
A78: 75 | B78: 5007 | C78: 31 | D78: 901512653 | E78: 31 | J78: DISTRIVARIEDADES LVM BQ SAS | K78: CL 34 4370 LC 116 117 | N78: 169 | O78: 2772689
A79: 76 | B79: 5007 | C79: 31 | D79: 901414576 | E79: 31 | J79: DORCAS INTERNACIONAL SAS | N79: 169 | O79: 15445378
A80: 77 | B80: 5007 | C80: 31 | D80: 70953009 | E80: #N/A | F80: #N/A | G80: #N/A | H80: #N/A | I80: #N/A | J80: DUVAN ROLANDO MONTES ATEHORUA | K80: #N/A | L80: #N/A | M80: #N/A | N80: 169 | O80: 2408014
A81: 78 | B81: 5007 | C81: 31 | D81: 900504846 | E81: 31 | J81: ECHEVERRI AMAYA SAS | K81: CL 31 N 41 38 | L81: 05 | M81: 360 | N81: 169 | O81: 1014285
A82: 79 | B82: 5007 | C82: 31 | D82: 901421572 | E82: #N/A | F82: #N/A | G82: #N/A | H82: #N/A | I82: #N/A | J82: ECOPLANET INVERSIONES S.A.S. | K82: #N/A | L82: #N/A | M82: #N/A | N82: 169 | O82: 229500
A83: 80 | B83: 5007 | C83: 31 | D83: 70697909 | E83: 13 | F83: GIRALDO | G83: GOMEZ | H83: EDWIN | I83: ALEXANDER | J83: EDWIN ALEXANDER GIRALDO GOMEZ | N83: 169 | O83: 2722668
A84: 81 | B84: 5007 | C84: 31 | D84: 70386448 | E84: #N/A | F84: #N/A | G84: #N/A | H84: #N/A | I84: #N/A | J84: ELKIN NORBAIRO VILLEGAS GOMEZ | K84: #N/A | L84: #N/A | M84: #N/A | N84: 169 | O84: 3610248
A85: 82 | B85: 5007 | C85: 31 | D85: 70828813 | E85: 13 | F85: GIRALDO | G85: NARANJO | H85: ELKIN | I85: OVIDIO | J85: ELKIN OVIDIO GIRALDO NARANJO | K85: CRA 52A N 45-33 BODEGA 901B | N85: 169 | O85: 2997029
A86: 83 | B86: 5007 | C86: 31 | D86: 72139503 | E86: 13 | F86: PACHECO | G86: POLO | H86: ELMER | I86: ENRIQUE | J86: ELMER ENRIQUE PACHECO POLO | K86: CR 16 12 26 | L86: 20 | M86: 001 | N86: 169 | O86: 3581298
A87: 84 | B87: 5007 | C87: 31 | D87: 901274295 | E87: #N/A | F87: #N/A | G87: #N/A | H87: #N/A | I87: #N/A | J87: ELOAH SAS | K87: #N/A | L87: #N/A | M87: #N/A | N87: 169 | O87: 194917
A88: 85 | B88: 5007 | C88: 31 | D88: 79310761 | E88: 13 | F88: HERNANDEZ | G88: PEÑA | H88: EMELIAS | J88: EMELIAS HERNANDEZ PEÑA | K88: CALLE 65 # 28-51 | N88: 169 | O88: 1615945
A89: 86 | B89: 5007 | C89: 31 | D89: 42155271 | E89: 13 | F89: ESCOBAR | G89: MARTINEZ | H89: SANDRA | I89: CATALINA | J89: ESCOBAR MARTINEZ SANDRA CATALINA | K89: C.CIAL LOS PAISAS LOCAL 188 | N89: 169 | O89: 1930756
A90: 87 | B90: 5007 | C90: 31 | D90: 800177119 | E90: 31 | J90: ESPUMADOS DEL LITORAL S.A. | K90: CL 110 9G 520 | L90: 08 | M90: 001 | N90: 169 | O90: 202246612
A91: 88 | B91: 5007 | C91: 31 | D91: 830054581 | E91: 31 | J91: ESTELAR EXPRESS S.A.S | N91: 169 | O91: 301700
A92: 89 | B92: 5007 | C92: 31 | D92: 890926803 | E92: #N/A | F92: #N/A | G92: #N/A | H92: #N/A | I92: #N/A | J92: ESTUDIO DE MODA S.A.S | K92: #N/A | L92: #N/A | M92: #N/A | N92: 169 | O92: 1428479
A93: 90 | B93: 5007 | C93: 31 | D93: 43514319 | E93: 13 | F93: MOLINA | G93: MURILLO | H93: FANNY | J93: FANNNY MOLINA MURILLO | K93: TV 32 SUR DG 32D 64 | N93: 169 | O93: 14566219
A94: 91 | B94: 5007 | C94: 31 | D94: 800149695 | E94: 31 | J94: FARMACIAS CRUZ VERDE SAS | N94: 169 | O94: 54400
A95: 92 | B95: 5007 | C95: 31 | D95: 1098671406 | E95: #N/A | F95: #N/A | G95: #N/A | H95: #N/A | I95: #N/A | J95: FELIX ANDRES BENITEZ GALVIS | K95: #N/A | L95: #N/A | M95: #N/A | N95: 169 | O95: 1325000
A96: 93 | B96: 5007 | C96: 31 | D96: 72312545 | E96: 13 | F96: ZULUAGA | G96: GOMEZ | H96: FERNEY | I96: ENRIQUE | J96: FERNEY ENRIQUE ZULUAGA GOMEZ | K96: CL 34 43 70 | L96: 08 | M96: 001 | N96: 169 | O96: 19590581
A97: 94 | B97: 5007 | C97: 31 | D97: 811012427 | E97: #N/A | F97: #N/A | G97: #N/A | H97: #N/A | I97: #N/A | J97: FERRETERIA LOS FIERROS | K97: #N/A | L97: #N/A | M97: #N/A | N97: 169 | O97: 1084193
A98: 95 | B98: 5007 | C98: 31 | D98: 901146913 | E98: #N/A | F98: #N/A | G98: #N/A | H98: #N/A | I98: #N/A | J98: FERRETERIA Y CACHARRERIA EMANUEL S.A.S. | K98: #N/A | L98: #N/A | M98: #N/A | N98: 169 | O98: 854588
A99: 96 | B99: 5007 | C99: 31 | D99: 23781159 | E99: 13 | F99: SUAREZ | G99: CASTILLO | H99: FLORINDA | J99: FLORINDA SUAREZ CASTILLO | K99: CR 9 27 03 | L99: 68 | M99: 276 | N99: 169 | O99: 20215895
A100: 97 | B100: 5007 | C100: 31 | D100: 1129485999 | E100: 13 | F100: Fonseca | G100: Jimenez | H100: Rosa | I100: Maria | J100: FONSECA JIMENEZ ROSA MARIA | N100: 169 | O100: 13331885
...

Sheet terceros
A1: 1 | B1: 2 | C1: 3 | D1: 4 | E1: 5 | F1: 6 | G1: 7 | H1: 8 | I1: 9 | J1: 10
A2: nit | B2: direccion | C2: codDpto | D2: codMunicipio | E2: tipo_doc | F2: razon | G2: apellido1 | H2: apellido2 | I2: nombre1 | J2: nombre2
A3: 901144165 | B3: CL 27 1 07 CAUCASIA ANTIOQUIA | C3: 05 | D3: 154 | E3: 31 | F3: COMPAÑÍA DE TRANSPORTE DE BEBIDAS S.
A4: 901360896 | B4: CALLE 19 12 A 06 | C4: 05 | D4: 380 | E4: 31 | F4: LUBRICANTES EL PAISA S.A.S
A5: 901183779 | B5: CL 12B 21 31 32 BOGOTA | C5: 11 | D5: 001 | E5: 31 | F5: CENTRO DE DIAGNOSTICO AUTOMOTOR SAN RAFAEL
A6: 901130988 | B6: CL 28 20 19 AV LUIS CRLOS GALAN | C6: 05 | D6: 360 | E6: 31 | F6: ESYS SOLUCIONES TECNOLOGICAS S.A.S
A7: 860011153 | B7: CR 45 94 72 | C7: 11 | D7: 001 | E7: 31 | F7: ARL POSITIVA COMPAÑÍA DE SEGUROS
A8: 802022973 | B8: CL 37 1 B 65 | C8: 23 | D8: 001 | E8: 31 | F8: INVERSIONES LOPEZ MIER S.A.S.
A9: 830065179 | B9: CR 58 43 SUR 83 INT 123 | C9: 05 | D9: 001 | E9: 31 | F9: SFA CEBAR S.A.S.
A10: 8364120 | B10: CL 29 40A 25 MONTERIA COL | C10: 23 | D10: 001 | E10: 13 | G10: NIÑO | H10: ALVAREZ | I10: ORLANDO
A11: 900336004 | B11: CL 37 1 B 65 | C11: 23 | D11: 001 | E11: 31 | F11: ADMINISTRADORA COLOMBIANA DE
A12: 830122566 | B12: KM 1 VIA CERETE | C12: 23 | D12: 162 | E12: 31 | F12: COLOMBIA TELECOMUNICACIONES S.A.
A13: 17356123 | B13: CR 43 P SUR 195 OF 1442 | C13: 23 | D13: 001 | E13: 13 | G13: ESCOBAR | H13: MEJIA | I13: EFRAIN
A14: 800157892 | B14: CR 74 79 19 | C14: 08 | D14: 001 | E14: 31 | F14: AUTO ROBLE LTDA.
A15: 892280013 | B15: CRA 27 B CENTRO | C15: 11 | D15: 001 | E15: 31 | F15: CAMARA DE COMERCIO DE SINCELEJO
A16: 900606809 | B16: CR 50 28 A 39 | C16: 05 | D16: 001 | E16: 31 | F16: M BELL S.A.S.
A17: 901182264 | B17: ANILLO VIAL KM 11MAS 520 MTS BG 3 | C17: 54 | D17: 001 | E17: 31 | F17: INDUSTRIAS KAMIPLAST S.A.S.
A18: 900302882 | B18: CL 21 20 52 P1 ST S08 SINCELEJO | C18: 70 | D18: 001 | E18: 31 | F18: SAVANAH RAE COLOMBIA S.A.S.
A19: 900644703 | B19: calle 100 1-25 | C19: 70 | D19: 001 | E19: 31 | F19: INTEGRAL DE BELLEZA CASA DEL ESTILISTA S.A.S
A20: 70696424 | B20: CL 110 9G 520 AV CIRCUNVALAR | C20: 08 | D20: 001 | E20: 13 | G20: CARO | H20: RAMIREZ | I20: NELSON | J20: OCTAVIO
A21: 72139503 | B21: CR 16 12 26 | C21: 20 | D21: 001 | E21: 13 | G21: PACHECO | H21: POLO | I21: ELMER | J21: ENRIQUE
A22: 900488656 | B22: Diago al 44 30 C 04 | C22: 05 | D22: 088 | E22: 31 | F22: VIPERS TECNOLOGIA S.A.S.
A23: 900551822 | B23: CRA 24 18 A 14 BARRIO CENTRO | C23: 08 | D23: 001 | E23: 31 | F23: ALMACEN LA GRANJA DE SAN MARCOS S. A. S
A24: 860020536 | B24: CL 12B 21 31 | C24: 11 | D24: 001 | E24: 31 | F24: BARDOT S.A.S
A25: 900192769 | B25: CL 37 1 B 65 | C25: 23 | D25: 001 | E25: 31 | F25: LLANTAS Y FILTROS SINU S.A.S.
A26: 890905032 | B26: CR 54 46 40 OF 304 | C26: 05 | D26: 001 | E26: 31 | F26: PREBEL S.A.
A27: 900345905 | B27: CL 38 41 71 P2 | C27: 08 | D27: 001 | E27: 31 | F27: GRUPO ISMA S.A.S
A28: 800209088 | B28: CL 43 1C 49 | C28: 70 | D28: 001 | E28: 31 | F28: VIPERS LTDA
A29: 890100725 | B29: CL 108 A 35 A 70 | C29: 08 | D29: 001 | E29: 31 | F29: HAMACAS EL ZAQUE S.A.
A30: 900577348 | B30: KM 36 AUTOPISTA MEDELLIN BOGOTA | C30: 05 | D30: 615 | E30: 31 | F30: MUNDI UTIL S.A.S.
A31: 860020609 | B31: AV I DUSTRIAL CL 19 6905 | C31: 11 | D31: 001 | E31: 31 | F31: LABORATORIOS SMART S A S
A32: 800179834 | B32: AV 37B 42 155 | C32: 05 | D32: 360 | E32: 31 | F32: INVERSIONES SUPPORT S. A.
A33: 70693137 | B33: KM 1 VIA CERETE | C33: 23 | D33: 162 | E33: 13 | G33: GOMEZ | H33: ALZATE | I33: WILLIAM | J33: JOSE
A34: 830512218 | B34: CL 38 4 A 184 MZA 01 | C34: 70 | D34: 001 | E34: 31 | F34: MEDIMARCAS S.A.S.
A35: 10230381 | B35: AV 68 30 06 SUR PS °2 BOGOTA | C35: 11 | D35: 001 | E35: 13 | G35: SUAREZ | H35: GRAJALES | I35: GIRALDO
A36: 70725876 | B36: CR 2 36 35 | C36: 23 | D36: 001 | E36: 13 | G36: LOPEZ | H36: VALENCIA | I36: EFREIN | J36: DE JESUS
A37: 891700037 | B37: CR 57 A 45 39 PS 2 | C37: 05 | D37: 001 | E37: 31 | F37: MAPFRE SEGUROS GENERALES DE COLOMBIA S
A38: 800094742 | B38: CL 38 4 A 184 BL B BG 22 PAR I DUSTRIAL | C38: 70 | D38: 001 | E38: 31 | F38: SURTILINEAS DEL CARIBE S.A.
A39: 8309207 | B39: CL 34 43 70 LC X | C39: 08 | D39: 001 | E39: 13 | G39: ARISTIZABAL | H39: ARISTIZABAL | I39: APOLINAR | J39: ANTONIO
A40: 901265090 | B40: CL 12 5 72 MOTILONES | C40: 54 | D40: 001 | E40: 31 | F40: INVERSIONES CARRASCAL MORA S.A.S
A41: 890903858 | B41: CL 25D 95A 13 | C41: 11 | D41: 001 | E41: 31 | F41: INDUSTRIA NACIONAL DE GASEOSAS S A
A42: 70696611 | B42: CR 3 36 78 | C42: 23 | D42: 001 | E42: 13 | G42: FRANCO | H42: DUQUE | I42: JOHN | J42: OCTAVIO
A43: 900300734 | B43: CR 16 12 26 VALLEDUPAR COL | C43: 20 | D43: 001 | E43: 31 | F43: INDUSTRIAS SIGNOS S.A.S.
A44: 890900608 | B44: CR51 14 52 | C44: 05 | D44: 001 | E44: 31 | F44: ALMACENES EXITO S A
A45: 10886574 | B45: CALLE 19 -23-28 CENTRO | C45: 23 | D45: 001 | E45: 13 | G45: PADILLA | H45: FLOREZ | I45: MARIO | J45: LUIS
A46: 892200015 | B46: CL 36 134 201 KM 6 | C46: 76 | D46: 001 | E46: 31 | F46: CONFASUCRE
A47: 890932458 | B47: CR 47 CL 75 85 INT (3019 | C47: 17 | D47: 001 | E47: 31 | F47: RESTREPO BERNAL JARAMILLO R.B.J. S.A.S.
A48: 900414975 | B48: KM 1 VIA CERETE | C48: 23 | D48: 162 | E48: 31 | F48: IMPORTADORA Y COMERCIALIZADORA
A49: 800066778 | B49: CR 44B 62 26 | C49: 08 | D49: 001 | E49: 31 | F49: PLASTICOS FAYCO SOCIEDAD ANONIMA
A50: 890937015 | B50: CL 22 CR 2Y3 | C50: 23 | D50: 001 | E50: 31 | F50: DISTRIBUIDORA TROPICANA S.A.S.
A51: 800153993 | B51: CR 68 A 24 B 10 | C51: 23 | D51: 001 | E51: 31 | F51: COMUNICACION CELULAR S A COMCEL S A
A52: 860007873 | B52: CR 34 17B 61 | C52: 11 | D52: 001 | E52: 31 | F52: HARTUNG Y COMPAÑIA SAS .
A53: 890903790 | B53: Cl 76 45A 104 | C53: 05 | D53: 360 | E53: 31 | F53: SEGUROS DE VIDA SURAMERICANA S.A.
A54: 890903407 | B54: CL 36 134 201 KM 6 | C54: 76 | D54: 001 | E54: 31 | F54: SEGUROS GENERALES SURAMERICANA S. A.
A55: 901008327 | B55: KM 45 VIA CIENAGA DE ORO CERETE | C55: 23 | D55: 162 | E55: 31 | F55: FABRIPOR S.A.S
A56: 890900104 | B56: CR 45 32D 135 | C56: 05 | D56: 380 | E56: 31 | F56: INCAMETAL S.A.S.
A57: 800183056 | B57: CR 2 2 25 | C57: 05 | D57: 154 | E57: 31 | F57: DISTRILECO CAUCASIA S.A.S
A58: 900334174 | B58: CL 79B 29 33 | C58: 11 | D58: 001 | E58: 31 | F58: THYMS COLOMBIA S.A.S.
A59: 7309544 | B59: CL 7 14 36 | C59: 11 | D59: 001 | E59: 13 | G59: ORTIZ | H59: VILLAMIL | I59: JOSELINO
A60: 60315600 | B60: CR3 2 28 BRR LOMITAS | C60: 54 | D60: 001 | E60: 13 | G60: ZARATE | H60: SAYAGO | I60: FANNY
A61: 811026142 | B61: CENTRO LOGISTICO SAN JERONIMO | C61: 23 | D61: 001 | E61: 31 | F61: DISTRIBUIDORA VENUS S.A.S.
A62: 900783490 | B62: CR 10 10 01 PS 3 | C62: 11 | D62: 001 | E62: 31 | F62: FABRIHOGAR SS SAS
A63: 15354493 | B63: CL 38 1B 58 | C63: 23 | D63: 001 | E63: 13 | G63: CARMONA | H63: LOPEZ | I63: IVAN | J63: DARIO
A64: 811008383 | B64: CR 51 14 52 | C64: 05 | D64: 001 | E64: 31 | F64: COSMETICOS SAMY S.A.
A65: 811035695 | B65: CR 58, 43 sur – 83 i t 123 | C65: 05 | D65: 001 | E65: 31 | F65: INTERNACIONAL DE BELLEZA S.A.S.
A66: 800167200 | B66: KM 1 VIA BOGOTA | C66: 25 | D66: 214 | E66: 31 | F66: ESPUMAS SANTAFE DE BOGOTA SAS
A67: 890101272 | B67: VIA 40 64 198 | C67: 08 | D67: 001 | E67: 31 | F67: SEMPERTEX DE COLOMBIA S A
A68: 890926933 | B68: CR 6 79 80 BG 2 | C68: 23 | D68: 001 | E68: 31 | F68: GRUPO LITORAL S.A.S.
A69: 10879972 | B69: CL 30 54 50 GAYABAL | C69: 05 | D69: 001 | E69: 13 | G69: GIRALDO | H69: RAMIREZ | I69: FELIX | J69: ALONSO
A70: 900621922 | B70: CR 56 B 49 A 29 LOC 801 | C70: 05 | D70: 001 | E70: 31 | F70: ESCULTORES DE MODA S.A.S.
A71: 900332596 | B71: CL 7 SUR 51A 21 | C71: 05 | D71: 001 | E71: 31 | F71: CREACIONES SEX S.A.S
A72: 900495915 | B72: CL 37 1B 79 | C72: 23 | D72: 001 | E72: 31 | F72: COMERCIALIZADORA MULTIMODA S.A.S
A73: 890101176 | B73: CENTRO EMPRESARIAL EL TRIUNFO KM 4 VIA PL | C73: 08 | D73: 001 | E73: 31 | F73: MEICO S.A.
A74: 802023305 | B74: CL 34 43 110 LC A | C74: 08 | D74: 001 | E74: 31 | F74: IMPORTACIONES NUEVO MILENIO S.A.S.
A75: 800212840 | B75: CL 90 11 13 P 6 | C75: 11 | D75: 001 | E75: 31 | F75: LOREAL COLOMBIA S.A.S
A76: 891001955 | B76: CRR 1 B 38 40 MONTERIA | C76: 23 | D76: 001 | E76: 31 | F76: DISTRIBUCIONES CARNAVAL SAS
A77: 901239963 | B77: CL 49 56B 18 | C77: 05 | D77: 001 | E77: 31 | F77: INDUSTRIAS ARFRA ZV S.A.S
A78: 901246694 | B78: KM 4 VIA PLNET RICA SAN GERONIMO | C78: 23 | D78: 001 | E78: 31 | F78: REPRESENTACIONES ARGOZ SAS
A79: 890922586 | B79: KM 5 VIA A GALAPA PAR INDUSTRIAL | C79: 08 | D79: 001 | E79: 31 | F79: TEXCOMERCIAL - TEXCO S.A.S.
A80: 800177119 | B80: CL 110 9G 520 | C80: 08 | D80: 001 | E80: 31 | F80: ESPUMADOS DEL LITORAL S.A.
A81: 800037800 | E81: 31 | F81: BANCO AGRARIO DE COLOMBIA S.A.
A82: 15928640 | E82: 13 | G82: PATIÑO | H82: RODRIGUEZ | I82: HECTOR | J82: WILLIAM
A83: 860000261 | E83: 31 | F83: COMPAÑIA NACIONAL DE LEVADURAS LEVAPAN S.A.
A84: 8103891 | E84: 13 | G84: ZULUAGA | H84: RAMIREZ | I84: CARLOS | J84: DAVID
A85: 900559921 | E85: 31 | F85: GANADERIA EL PERU S.A.S.
A86: 800136105 | B86: CL 67 7 35 TO AP 2 | E86: 31 | F86: MISION TEMPORAL LTDA
A87: 830099564 | E87: 31 | F87: ASOCIACION DE PROFESIONALES Y
A88: 812005190 | B88: CL40 1 B 79 | C88: 23 | D88: 001 | E88: 31 | F88: DEPOSITO DE DROGAS PARIS LTDA.
A89: 900328341 | E89: 31 | F89: SOCIEDAD COLOMBIANA DE CONSTRUCCIONES
A90: 900704791 | E90: 31 | F90: GRUPO TV MAX S.A.S.
A91: 900813836 | E91: 31 | F91: DISTRIBUCIONES AML S.A.S.
A92: 900814762 | E92: 31 | F92: LACTEOS DE LA GRANJA S.A.S
A93: 900750425 | E93: 31 | F93: ARROCERA PROPADDY S.A.S
A94: 900838474 | B94: CRA 10 17 70 | E94: 31 | F94: ASOCIADOS GARCIA CASTRO S.A.S.
A95: 900896114 | B95: KM1 AV TRONCAL VIA CAUCASIA | E95: 31 | F95: CONCORPLANET. MED
A96: 900948826 | E96: 31 | F96: AJV INGENIEROS SAS
A97: 901040678 | B97: CARR 19 # 19 A 28 | E97: 31 | F97: 3EFFORT S.A.S.
A98: 901360784 | E98: 31 | F98: LACTEOS WDJ SAS
A99: 900499976 | E99: 31 | F99: CONSTRUFERRETERO S.A.S
A100: 900163354 | B100: DG . 17 # 18 - 10 | E100: 31 | F100: ARROCERA FORMOSA S.A.S. EN REESTRUCTURACION
...

Sheet 1003 OK
D1: 1003 Retenciones en la fuente que le practicaron
A2: 1003 | B2: Retenciones en la fuente que le practicaron V7
A4: Concepto | B4: Tipo de documento | C4: Número identificación | D4: DV | E4: Primer apellido del informado | F4: Segundo apellido del informado | G4: Primer nombre del informado | H4: Otros nombres del informado | I4: Razón social informado | J4: Dirección | K4: Código dpto. | L4: Código mcp | M4: Valor acumulado del pago o abono sujeto a retención en la fuente | N4: Retención en la fuente que le practicaron
N14: =+M14*0.04 -> 0

Sheet 1005 OK
I1: IVA EN COMOPRAS DESCONTANDO LA NOTA CREDITO EN COMPRAS
A2: 1005 | B2: Impuesto a las ventas por pagar (descontable) V7 | I2: DESCONTANDO EL IVA DE LA NOTA CREDITO
A3: Sin cuantias minimas
A4: Tipo de Documento | B4: Numero de identificación del informado | C4: DV | D4: Primer apellido del informado | E4: Segundo apellido del informado | F4: Primer nombre del informado | G4: Otros nombres del informado | H4: Razón social informado | I4: Impuesto descontable | J4: IVA resultante por devoluciones en ventas anuladas, rescindidas o resueltas
B5: 892200994 | H5: ALMACEN FERROMOTORES S.A. | I5: 17490203 | J5: 0 | K5: 0
B6: 900623201 | H6: CACHARRERIA MUNDIAL S.A.S. | I6: 6071660 | J6: 0 | K6: 0
B7: 901281934 | H7: CEMENTOS ORIENTE SAS ZOMAC | I7: 2648695 | J7: 0 | K7: 0
B8: 890900943 | H8: COLOMBIANA DE COMERCIO S.A. | I8: 6662850 | J8: 0 | K8: 0
B9: 800066275 | H9: COMERCIAL J.F.I. S.A.S | I9: 451953 | J9: 0 | K9: 0
B10: 900205377 | H10: COMERCIALIZADORA AGROHIERROS S.A | I10: 13079508 | J10: 0 | K10: 0
B11: 900918651 | H11: COMERCIALIZADORA MAC ROYAL - ZOMAC S.A.S. | I11: 7592 | J11: 0 | K11: 0
B12: 900507746 | H12: CONCREACEROS S.A.S. | I12: 9777355 | J12: 0 | K12: 0
B13: 901359284 | H13: COVERFIL S.A.S | I13: 208288 | J13: 0 | K13: 0
B14: 901145515 | H14: DA&ROCH DISTRIBUCIONES S.A.S. | I14: 314861 | J14: 0 | K14: 0
B15: 800023002 | H15: DISREL SAS DISTRIBUCIONES Y REPRESENTACIONES ELEC | I15: 2310215 | J15: 0 | K15: 0
B16: 800185467 | H16: DISTHINNER SAS | I16: 1842521 | J16: 0 | K16: 0
... B61: 800098601 | H61: UNIFEL S.A. | I61: 36985879 | J61: 0 | K61: 0
B62: 79148397 | D62: MOJOCOA | E62: PARADA | F62: JUAN | G62: CARLOS | I62: 878519 | J62: 0 | K62: 0
B63: 10934103 | D63: CORREA | E63: CASTRO | F63: LUIS | G63: CARLOS | I63: 19121432 | J63: 0 | K63: 0
B64: 43785419 | D64: GALLEGO | E64: GOMEZ | F64: MARIA | G64: FLORELBA | I64: 323350 | J64: 0 | K64: 0
B65: 70696078 | D65: GALLEGO | E65: GOMEZ | F65: WILLIAM | G65: DARIO | I65: 59918 | J65: 0 | K65: 0
B66: 70353742 | D66: GIRALDO | E66: MARIN | F66: JOHNY | G66: ANDRES | I66: 326933881 | J66: 0 | K66: 0
B67: 1124060096 | D67: SERHAN | E67: TOUFIC | F67: RABIH | I67: 4485973 | J67: 0 | K67: 0
B68: 9868376 | D68: ZULUAGA | E68: SANCHEZ | F68: FRANK | G68: FERNANDO | I68: 320940 | J68: 0 | K68: 0
B69: 13745511 | D69: PARDO | E69: MILLAN | F69: RUFINO | I69: 97259 | J69: 0 | K69: 0
B70: 70725876 | D70: LOPEZ | E70: VALENCIA | F70: EFREN | G70: DE JESUS | I70: 417042 | J70: 0 | K70: 0
B71: 98483586 | D71: VALENCIA | E71: GARRO | F71: FABIAN | I71: 2315342 | J71: 0 | K71: 0
B72: 1022358313 | D72: ACUA | E72: RODRIGUEZ | F72: CESAR | G72: ALDRIN | I72: 614706 | J72: 0 | K72: 0
B73: 1063169167 | D73: PADILLA | E73: NAVAJA | F73: LINA | G73: MARIA | I73: 463009 | J73: 0 | K73: 0
B74: 1129485999 | D74: FONSECA | E74: JIMENEZ | F74: ROSA | G74: MARIA | I74: 10842805 | J74: 0 | K74: 0
I75: 7.5365094e+08

Sheet 1006 OK
B2: 1006 | C2: Impuesto a las ventas por pagar (generado) e impuesto al consumo V8
B3: El valor del IVA generado y/o el impuesto al consumo de las operaciones donde el valor acumulado del ingreso hubiese sido igual o superior a quinientos mil pesos ($ 500.000)
B4: Tipo de Documento | C4: Numero de identificación | D4: DV | E4: Primer apellido del informado | F4: Segundo apellido del informado | G4: Primer nombre del informado | H4: Otros nombres del informado | I4: Razón social informado | J4: Impuesto generado | K4: IVA recuperado por operaciones en devoluciones en compras anuladas, rescindidas o resueltas | L4: Impuesto al consumo
A5: 1 | B5: 13 | C5: 1079940222 | E5: .CABALLERO | F5: MONTENEGRO | G5: JUAN | H5: MANUEL | J5: 35126 | K5: 0 | L5: 0
A6: 2 | B6: 13 | C6: 1079937378 | E6: .CANTILLO | F6: SANTOS | G6: JESUS | J6: 32013 | K6: 0 | L6: 0
A7: 3 | B7: 13 | C7: 30177198 | E7: .CASTRO | F7: MONTERO | G7: LUZ | J7: 71849 | K7: 0 | L7: 0
A8: 4 | B8: 13 | C8: 1079931569 | E8: .CRESPO | F8: VILLA | G8: CASILDA | J8: 18122 | K8: 0 | L8: 0
A9: 5 | B9: 13 | C9: 1004121069 | E9: .PASION | F9: MARTINEZ | G9: MARIA | H9: EUGENIA | J9: 41864 | K9: 0 | L9: 0
A10: 6 | B10: 13 | C10: 1004120997 | E10: .RODRIGUEZ | F10: RODRIGUEZ | G10: GLENDA | J10: 19080 | K10: 0 | L10: 0
A11: 7 | B11: 13 | C11: 22563210 | E11: ABDALA | F11: DE AVILA | G11: YULIETH | J11: 6371 | K11: 0 | L11: 0
A12: 8 | B12: 13 | C12: 1002302504 | E12: ACEVEDO | F12: MEZA | G12: LUZ | J12: 55435 | K12: 0 | L12: 0
A13: 9 | B13: 13 | C13: 1082844786 | E13: ACEVEDO | G13: YEISON | J13: 16142 | K13: 0 | L13: 0
A14: 10 | B14: 13 | C14: 1004122824 | E14: ACOSTA | F14: PALLARES | G14: CAROLINA | J14: 13763 | K14: 0 | L14: 0
A15: 11 | B15: 13 | C15: 1004123866 | E15: ACOSTA | F15: CANTILLO | G15: CESAR | H15: CAMILO | J15: 19734 | K15: 0 | L15: 0
A16: 12 | B16: 13 | C16: 1079911618 | E16: ACOSTA | G16: MARIA | H16: ELBIRA | J16: 48713 | K16: 0 | L16: 0
A17: 13 | B17: 13 | C17: 1079914290 | E17: ACOSTA | F17: PERTUZ | G17: LUZ | H17: NEIRA | J17: 47101 | K17: 0 | L17: 0
A18: 14 | B18: 13 | C18: 1079932236 | E18: ACOSTA | F18: MONTENEGRO | G18: NEIDER | J18: 15232 | K18: 0 | L18: 0
A19: 15 | B19: 13 | C19: 1079934441 | E19: ACOSTA | G19: YOLANDA | J19: 32715 | K19: 0 | L19: 0
A20: 16 | B20: 13 | C20: 1079935537 | E20: ACOSTA | F20: TORREJANO | G20: LUDYS | J20: 18170 | K20: 0 | L20: 0
A21: 17 | B21: 13 | C21: 1079941789 | E21: ACOSTA | F21: OSORIO | G21: AURA | J21: 4854 | K21: 0 | L21: 0
A22: 18 | B22: 13 | C22: 1082044949 | E22: ACOSTA | F22: VALLE | G22: YURANIS | J22: 65462 | K22: 0 | L22: 0
A23: 19 | B23: 13 | C23: 1082046200 | E23: ACOSTA | F23: VARELA | G23: WENDY | J23: 47261 | K23: 0 | L23: 0
A24: 20 | B24: 13 | C24: 1082046214 | E24: ACOSTA | G24: JESUS | J24: 13891 | K24: 0 | L24: 0
A25: 21 | B25: 13 | C25: 1127573690 | E25: ACOSTA | G25: MARIA | H25: ALEXANDRA | J25: 9117 | K25: 0 | L25: 0
A26: 22 | B26: 13 | C26: 1140849890 | E26: ACOSTA | G26: LILA | J26: 7824 | K26: 0 | L26: 0
A27: 23 | B27: 13 | C27: 1143138834 | E27: ACOSTA | F27: CAMARGO | G27: ENITH | J27: 61423 | K27: 0 | L27: 0
A28: 24 | B28: 13 | C28: 1151923 | E28: ACOSTA | F28: VACA | G28: JULIO | H28: CESAR | J28: 231513 | K28: 0 | L28: 0
A29: 25 | B29: 13 | C29: 19863307 | E29: ACOSTA | F29: ESCORCHA | G29: LUISBETH | H29: YOHANA | J29: 37952 | K29: 0 | L29: 0
A30: 26 | B30: 13 | C30: 22638114 | E30: ACOSTA | F30: SANTODOMINGO | G30: CRISTINA | J30: 9771 | K30: 0 | L30: 0
A31: 27 | B31: 13 | C31: 26825760 | E31: ACOSTA | F31: OROZCO | G31: MAUDIS | J31: 65047 | K31: 0 | L31: 0
A32: 28 | B32: 13 | C32: 26881053 | E32: ACOSTA | G32: YESSICA | J32: 5812 | K32: 0 | L32: 0
A33: 29 | B33: 13 | C33: 32691267 | E33: ACOSTA | F33: BROCHERO | G33: LUZ | H33: MARINA | J33: 132457 | K33: 0 | L33: 0
A34: 30 | B34: 13 | C34: 57300706 | E34: ACOSTA | F34: YANCY | G34: EDITH | J34: 367227 | K34: 0 | L34: 0
A35: 31 | B35: 13 | C35: 57305786 | E35: ACOSTA | F35: BOLAÑO | G35: JUANA | J35: 95639 | K35: 0 | L35: 0
A36: 32 | B36: 13 | C36: 57309594 | E36: ACOSTA | F36: BOLAÑO | G36: YULIS | H36: JOHANA | J36: 107613 | K36: 0 | L36: 0
A37: 33 | B37: 13 | C37: 1079936802 | E37: ACUNA | F37: JIMENEZ | G37: WENDY | J37: 7105 | K37: 0 | L37: 0
A38: 34 | B38: 13 | C38: 57307400 | E38: ACUNA | G38: AURA | H38: MARIA | J38: 9245 | K38: 0 | L38: 0
A39: 35 | B39: 13 | C39: 1010150212 | E39: ACUÑA | F39: MERCADO | G39: VANESA | J39: 3992 | K39: 0 | L39: 0
A40: 36 | B40: 13 | C40: 1081760820 | E40: ACUÑA | F40: MARTINEZ | G40: CELIA | J40: 21507 | K40: 0 | L40: 0
A41: 37 | B41: 13 | C41: 1082044435 | E41: ACUÑA | F41: DE LA MARCA | G41: ENA | J41: 23582 | K41: 0 | L41: 0
A42: 38 | B42: 13 | C42: 1083040780 | E42: ACUÑA | F42: GARIZADO | G42: MARIO | J42: 7712 | K42: 0 | L42: 0
A43: 39 | B43: 13 | C43: 39098545 | E43: ACUÑA | F43: CORTINA | G43: BELIA | J43: 52961 | K43: 0 | L43: 0
A44: 40 | B44: 13 | C44: 7598401 | E44: ACUÑA | F44: GIL | G44: YAMITH | J44: 9181 | K44: 0 | L44: 0
A45: 41 | B45: 13 | C45: 85433507 | E45: ACUÑA | F45: REYES | G45: GILBERTO | H45: JOSE | J45: 316138 | K45: 0 | L45: 0
A46: 42 | B46: 13 | C46: 22636911 | E46: AFRICANO | F46: CHARRIZ | G46: NELIDA | J46: 78139 | K46: 0 | L46: 0
A47: 43 | B47: 13 | C47: 1193223497 | E47: AGUAS | F47: MARTINEZ | G47: BRIAN | H47: JOSE | J47: 26265 | K47: 0 | L47: 0
A48: 44 | B48: 13 | C48: 7142469 | E48: AGUIRRE | G48: ANIVAL | J48: 10857 | K48: 0 | L48: 0
A49: 45 | B49: 13 | C49: 1010126344 | E49: AHUMADA | F49: PAYAREZ | G49: JHONYS | J49: 107821 | K49: 0 | L49: 0
A50: 46 | B50: 13 | C50: 1081212482 | E50: AHUMADA | F50: ACOSTA | G50: DAIRO | H50: JOSE | J50: 4790 | K50: 0 | L50: 0
A51: 47 | B51: 13 | C51: 1083572468 | E51: AHUMADA | G51: KEVIN | J51: 15487 | K51: 0 | L51: 0
A52: 48 | B52: 13 | C52: 1084738629 | E52: AHUMADA | F52: NOGUERA | G52: YESENIA | H52: PAOLA | J52: 11161 | K52: 0 | L52: 0
A53: 49 | B53: 13 | C53: 9877508 | E53: AHUMADA | F53: CASTRO | G53: CESAR | J53: 12182 | K53: 0 | L53: 0
A54: 50 | B54: 13 | C54: 72334163 | E54: ALARCON | F54: POLO | G54: JAVIER | J54: 166050 | K54: 0 | L54: 0
A55: 51 | B55: 13 | C55: 1082849470 | E55: ALBORNOS | F55: CANTILLO | G55: ELSI | J55: 56569 | K55: 0 | L55: 0
A56: 52 | B56: 13 | C56: 84080740 | E56: ALCALA | G56: ALVARO | H56: MANUEL | J56: 11703 | K56: 0 | L56: 0
A57: 53 | B57: 13 | C57: 57308029 | E57: ALDANA | F57: RODRIGUEZ | G57: ROXANA | J57: 29234 | K57: 0 | L57: 0
A58: 54 | B58: 13 | C58: 1079938807 | E58: ALEJANDRO | F58: FONTALVO | G58: JOSE | J58: 33529 | K58: 0 | L58: 0
A59: 55 | B59: 13 | C59: 26814039 | E59: ALEMAN | F59: CANTILLO | G59: EDITH | J59: 15312 | K59: 0 | L59: 0
A60: 56 | B60: 13 | C60: 1079933355 | E60: ALFARO | F60: DE LA CRUZ | G60: MILENA | J60: 53200 | K60: 0 | L60: 0
A61: 57 | B61: 13 | C61: 1079912752 | E61: ALFONSO | F61: SILVA | G61: EMIL | J61: 44706 | K61: 0 | L61: 0
A62: 58 | B62: 13 | C62: 3741927 | E62: ALGARIN | F62: PALMA | G62: GABRIEL | J62: 7776 | K62: 0 | L62: 0
A63: 59 | B63: 13 | C63: 1079885053 | E63: ALMANZA | F63: RAMBAL | G63: ALDO | J63: 13891 | K63: 0 | L63: 0
A64: 60 | B64: 13 | C64: 1079938769 | E64: ALTAHONA | F64: CASTAÑEDA | G64: IVAN | H64: DAVID | J64: 11001 | K64: 0 | L64: 0
A65: 61 | B65: 13 | C65: 44150013 | E65: ALTAMAR | F65: MARENGO | G65: HANITH | J65: 14018 | K65: 0 | L65: 0
A66: 62 | B66: 13 | C66: 44160013 | E66: ALTAMAR | G66: HANITH | J66: 9388 | K66: 0 | L66: 0
A67: 63 | B67: 13 | C67: 26812747 | E67: ALVARADO | G67: FLORENZA | J67: 14354 | K67: 0 | L67: 0
A68: 64 | B68: 13 | C68: 32682473 | E68: ALVARADO | G68: GRACIELA | J68: 5908 | K68: 0 | L68: 0
A69: 65 | B69: 13 | C69: 57116296 | E69: ALVARADO | F69: VERGARA | G69: ROSA | H69: MARIA | J69: 10666 | K69: 0 | L69: 0
A70: 66 | B70: 13 | C70: 1004213282 | E70: ALVARES | F70: MANGA | G70: KEVIN | H70: ANDRES | J70: 8766 | K70: 0 | L70: 0
A71: 67 | B71: 13 | C71: 1073979146 | E71: ALVARES | G71: SHEIDY | J71: 13779 | K71: 0 | L71: 0
A72: 68 | B72: 13 | C72: 1079912370 | E72: ALVARES | F72: ACOSTA | G72: KELLIS | H72: JHOANA | J72: 20533 | K72: 0 | L72: 0
A73: 69 | B73: 13 | C73: 1082046215 | E73: ALVARES | F73: CASTRO | G73: KARINA | J73: 37872 | K73: 0 | L73: 0
A74: 70 | B74: 13 | C74: 1083572481 | E74: ALVARES | G74: CORALIS | J74: 5109 | K74: 0 | L74: 0
A75: 71 | B75: 13 | C75: 26881257 | E75: ALVARES | F75: MIRANDA | G75: OMAIRA | H75: LUZ | J75: 157141 | K75: 0 | L75: 0
A76: 72 | B76: 13 | C76: 1004122098 | E76: ALVAREZ | F76: PERALTA | G76: ARLEY | J76: 5588 | K76: 0 | L76: 0
A77: 73 | B77: 13 | C77: 1004122625 | E77: ALVAREZ | F77: ANDRADE | G77: KENDY | J77: 9580 | K77: 0 | L77: 0
A78: 74 | B78: 13 | C78: 1007162183 | E78: ALVAREZ | F78: MEDINA | G78: EBERTO | J78: 72040 | K78: 0 | L78: 0
A79: 75 | B79: 13 | C79: 1007162716 | E79: ALVAREZ | G79: TANIA | H79: MILENA | J79: 62955 | K79: 0 | L79: 0
A80: 76 | B80: 13 | C80: 1048210921 | E80: ALVAREZ | F80: DE LA HOZ | G80: LEONARDO | J80: 103782 | K80: 0 | L80: 0
A81: 77 | B81: 13 | C81: 1079912123 | E81: ALVAREZ | F81: VALENCIA | G81: ATILIO | H81: JOSE | J81: 21603 | K81: 0 | L81: 0
A82: 78 | B82: 13 | C82: 1079912658 | E82: ALVAREZ | F82: TORREGROZA | G82: LINA | J82: 92445 | K82: 0 | L82: 0
A83: 79 | B83: 13 | C83: 1079915043 | E83: ALVAREZ | F83: VALENCIA | G83: YOXANDRA | J83: 112324 | K83: 0 | L83: 0
A84: 80 | B84: 13 | C84: 1079934623 | E84: ALVAREZ | G84: JESITH | J84: 9021 | K84: 0 | L84: 0
A85: 81 | B85: 13 | C85: 1079937318 | E85: ALVAREZ | G85: MORELIA | J85: 10570 | K85: 0 | L85: 0
A86: 82 | B86: 13 | C86: 1082044068 | E86: ALVAREZ | G86: DANIEL | J86: 11081 | K86: 0 | L86: 0
A87: 83 | B87: 13 | C87: 1082045444 | E87: ALVAREZ | F87: PALLARES | G87: DANIELA | H87: MARIA | J87: 5588 | K87: 0 | L87: 0
A88: 84 | B88: 13 | C88: 1083572510 | E88: ALVAREZ | G88: JORGE | J88: 9340 | K88: 0 | L88: 0
A89: 85 | B89: 13 | C89: 19618617 | E89: ALVAREZ | F89: FONTALVO | G89: JULIO | H89: CESAR | J89: 64664 | K89: 0 | L89: 0
A90: 86 | B90: 13 | C90: 26881407 | E90: ALVAREZ | F90: TORREGROSA | G90: ELEDIS | H90: JUDITH | J90: 6211 | K90: 0 | L90: 0
A91: 87 | B91: 13 | C91: 36550688 | E91: ALVAREZ | F91: VALLE | G91: MARIA | J91: 23487 | K91: 0 | L91: 0
A92: 88 | B92: 13 | C92: 57305397 | E92: ALVAREZ | F92: CANTILLO | G92: CILIA | J92: 4902 | K92: 0 | L92: 0
A93: 89 | B93: 13 | C93: 7125976 | E93: ALVAREZ | G93: KEINER | J93: 15639 | K93: 0 | L93: 0
A94: 90 | B94: 13 | C94: 9877593 | E94: ALVAREZ | F94: POLO | G94: LEONARDO | H94: JOSE | J94: 53392 | K94: 0 | L94: 0
A95: 91 | B95: 13 | C95: 1047481782 | E95: ALVEA | G95: ITSVAN | J95: 16861 | K95: 0 | L95: 0
A96: 92 | B96: 13 | C96: 57290034 | E96: ALZATE | G96: ISAURA | J96: 9372 | K96: 0 | L96: 0
A97: 93 | B97: 13 | C97: 70257137 | E97: ALZATE | F97: MARIN | G97: CARLOS | H97: MARIO | J97: 241571 | K97: 0 | L97: 0
A98: 94 | B98: 13 | C98: 1002072874 | E98: AMADOR | G98: SANTY | J98: 14370 | K98: 0 | L98: 0
A99: 95 | B99: 13 | C99: 1063081624 | E99: AMADOR | F99: ORTIZ | G99: DANIEL | J99: 8079 | K99: 0 | L99: 0
A100: 96 | B100: 13 | C100: 72269358 | E100: AMADOR | G100: RAFAEL | J100: 22992 | K100: 0 | L100: 0
A101: 97 | B101: 13 | C101: 32773651 | E101: AMPARO | F101: YANCY | G101: LUZ | J101: 10139 | K101: 0 | L101: 0
...

Sheet iva_ventas
A1: NIT Receptor | B1: Nombre Receptor | C1: iva
A2: 1007162093 | B2: VIVIANA ISABEL OROZCO DAZA | C2: 353600
A3: 1004226846 | B3: DIOSA CARRANZA MAZA | C3: 25195
A4: 26814854 | B4: ABA LUZ CABALLERO | C4: 7983
A5: 901363836 | B5: ABBACÜS BUSINESS SOLUTIONS SAS | C5: 308934
A6: 7598243 | B6: ABEL ANTONIO OROZCO BARON | C6: 49448
A7: 9876305 | B7: ABEL ORTEGA | C7: 53184
A8: 7594734 | B8: ABELARDO CANTILLO ESCALANTE | C8: 122941
A9: 9875160 | B9: ABELARDO ENRIQUE RODRIGUEZ MEDINA | C9: 127731
A10: 5080050 | B10: ABELARDO PABON PACHECO | C10: 237420
A11: 1091683107 | B11: ABRAHAM NAVARRO | C11: 81923
A12: 1081027111 | B12: ABRHAN JOSE NAVARRO PABON | C12: 147657
A13: 49720962 | B13: ADA BORJA DE LA HOZ | C13: 27191
... A630: 1079932094 | B630: CARLOS SEGUNDO MORRON PALMA | C630: 30895
A631: 10010890 | B631: CARLOS SEPULVEDA | C631: 24572
A632: 9875845 | B632: CARLOS SEVERINI | C632: 20996
A633: 1102862027 | B633: CARLOS SOLANO ANAYA | C633: 5588
A634: 7591238 | B634: CARLOS TOMAS SEVERINI CABALLERO | C634: 8702
A635: 1043010456 | B635: CARLOS YEJAS GONZALES | C635: 55180
A636: 7599566 | B636: CARLOS ZAMBRANO | C636: 33689
A637: 1079912216 | B637: CARLOTA AREVALO | C637: 31821
A638: 57308636 | B638: CARLOTA AREVALO CHARRIZ | C638: 47348
A639: 57305548 | B639: CARMELA CASTAÑEDA PARRA | C639: 23359
A640: 26816863 | B640: CARMEN AMPARO LARA DE LA CRUZ | C640: 111429
A641: 22734544 | B641: CARMEN BELIZA CAMPO ORTIZ | C641: 23471
A642: 32732260 | B642: CARMEN BORNACELIS | C642: 7504
A643: 1079913368 | B643: CARMEN CABALLERO CAMPO | C643: 87480
... A694: 1082890050 | B694: CATALINA ESCORCIA | C694: 12438
A695: 84453560 | B695: CEBALLOS SANDOVAL SAMIR ALBERTO | C695: 145789
A696: 26814869 | B696: CECILIA CAALLERO POLO | C696: 9101
A697: 1004120481 | B697: CECILIA CASTRO LLANOS | C697: 45712
A698: 26825482 | B698: CECILIA COLLAZO | C698: 44215
A699: 57308412 | B699: CECILIA ELENA BENAVIDES MEZA | C699: 209160
A700: 57306036 | B700: CECILIA ISABEL DE LA CRUZ PINEDA | C700: 76447
A701: 32782214 | B701: CECILIA ORTEGA MUÑOZ | C701: 31470
A702: 1004380569 | B702: CECILIA SANCHEZ SABALETA | C702: 22592
A703: 1081760820 | B703: CELIA ACUÑA MARTINEZ | C703: 21507
A704: 57303815 | B704: CELIA GAMARRA | C704: 28867
A705: 57309215 | B705: CELIA VALLE MERIÑO | C705: 178824
A706: 45444607 | B706: CELIA YAMITH DE LA CRUZ GARCIA | C706: 307018
A707: 1079931974 | B707: CELINA DE LA ROSA CHARRIS | C707: 27957
... A1488: 1083573218 | B1488: GUSTAVO OLIVO TORREGROZA | C1488: 33242
A1489: 5079348 | B1489: GUSTAVO RAFAEL LLANOS GARCIA | C1489: 31933
A1490: 4356607 | B1490: GUSTAVO SALAZAR ZULUAGA | C1490: 387935
A1491: 1082841794 | B1491: GUSTAVO SEVERINI PABON . | C1491: 117800
A1492: 1079914668 | B1492: GUSTAVO VARELA OROZCO | C1492: 829204
A1493: 1081826196 | B1493: HAMERSSON DAVID VELEZCO CANTILLO | C1493: 7504
A1494: 44160013 | B1494: HANITH ALTAMAR | C1494: 9388
A1495: 44150013 | B1495: HANITH ALTAMAR MARENGO | C1495: 14018
A1496: 1007833181 | B1496: HAROL ALBERTO HERNANDEZ MARTINEZ | C1496: 7472
A1497: 1079913448 | B1497: HAROL RADA POLO | C1497: 26121
A1498: 1007162055 | B1498: HAROLD ANDRES ARIZA ORTEGA | C1498: 116555
A1499: 1118469059 | B1499: HECTOR CARVAJAL RODRIGUEZ | C1499: 5780
A1500: 1148707006 | B1500: HECTOR CARVAL | C1500: 14050
A1501: 7596515 | B1501: HECTOR GAMARRA VEGA | C1501: 17371
... A2541: 1082933743 | B2541: LUIS FERNANDO PERTUZ POLO | C2541: 13651
A2542: 84453726 | B2542: LUIS FERNANDO SALAS ROMO | C2542: 9899
A2543: 1079936653 | B2543: LUIS GARCIA GARCIA | C2543: 38000
A2544: 1082251911 | B2544: LUIS GUILLERMO PEÑA AGUILAR | C2544: 34807
A2545: 900699108 | B2545: LUIS GUILLERMO SAGANOME E HIJO SAS | C2545: 56202
A2546: 9877121 | B2546: LUIS GUTIERREZ GAMERO | C2546: 15328
A2547: 1079912760 | B2547: LUIS GUTIERREZ MARBOL | C2547: 4630
A2548: 1143231957 | B2548: LUIS JIMENEZ AVENDAÑO | C2548: 8047
A2549: 1079912362 | B2549: LUIS JOSE BARRIOS JIMENEZ | C2549: 32715
A2550: 7594179 | B2550: LUIS JOSUE PALACIO RODRIGUEZ | C2550: 56202
A2551: 7596399 | B2551: LUIS MANGA MENDOZA | C2551: 62269
A2552: 1081762010 | B2552: LUIS MARTINEZ | C2552: 54286
A2553: 1004122167 | B2553: LUIS MIGUEL CANTILLO GUTIERREZ | C2553: 33114
A2554: 9877684 | B2554: LUIS MIGUEL GUTIERREZ | C2554: 23525
... A2658: 26671313 | B2658: MALVIRIS ESCORCIA OROZCO | C2658: 18234
A2659: 84451382 | B2659: MANCILLA VIZCAINO OSVALDO RAFAEL | C2659: 6786
A2660: 1081760899 | B2660: MANIRA ESTHER MARTINEZ VALLE | C2660: 357264
A2661: 900970124 | B2661: MANITAS DE AMOR | C2661: 32763
A2662: 57306383 | B2662: MANOLAIMA POLO CERVANTES | C2662: 11256
A2663: 7590674 | B2663: MANUEL ANTONIO GARCIA CORONADO | C2663: 49895
A2664: 9877541 | B2664: MANUEL ANTONIO SANCHEZ | C2664: 43109
A2665: 72270239 | B2665: MANUEL BOCANEGRA | C2665: 83648
A2666: 72270270 | B2666: MANUEL BOCANEGRA GARCIA | C2666: 8303
A2667: 1079941386 | B2667: MANUEL CASTRO MERCADO | C2667: 6115
A2668: 1004121620 | B2668: MANUEL DE JESUS OROZCO JIMENEZ | C2668: 8622
A2669: 5078578 | B2669: MANUEL DE LA HOZ GUTIERrEZ | C2669: 64903
A2670: 7592999 | B2670: MANUEL DE LA ROSA RUDAS FERREIRA | C2670: 95798
A2671: 1004122642 | B2671: MANUEL ENRIQUE PEREZ PAEZ | C2671: 136193
... A3500: 1079934504 | B3500: ROMARIO GARCIA | C3500: 25913
A3501: 84452945 | B3501: ROMERO SALAS ALFONSO JOSE | C3501: 20813
A3502: 1083573145 | B3502: RONAL CHARRIS | C3502: 6371
A3503: 28755548 | B3503: RONAL ENRRIQUE VERA MOLINA | C3503: 13252
A3504: 1083003638 | B3504: RONAL OSPINO JULIO | C3504: 36116
A3505: 1004121370 | B3505: RONALDO CREZPO | C3505: 3752
A3506: 1083574021 | B3506: RONALDO DAVID CHIQUILLO CANTILLO | C3506: 252476
A3507: 1001798730 | B3507: RONALDO DE LA HOZ | C3507: 60082
A3508: 1079911543 | B3508: RONALDO VARGAS PEREZ | C3508: 56872
A3509: 1083573246 | B3509: ROSA ANGELICA IVAÑEZ | C3509: 106336
A3510: 1126119600 | B3510: ROSA ASENCIO DE LA HOZ | C3510: 12613
A3511: 1129530839 | B3511: ROSA BURGOS CARRASQUIEL | C3511: 222599
A3512: 1140867317 | B3512: ROSA CAMPO PABON | C3512: 3513
A3513: 1079912433 | B3513: ROSA DINA OROZCO POLO | C3513: 7712
... A4251: 57306222 | B4251: ZUNILDA VARGAS MONTENEGRO | C4251: 78874
C4253: =SUM(C2:C4251) -> 402689387
C4255: 402689387

Sheet 1007 OK
C2: 1007 | D2: Ingresos recibidos V9 | K2: 169 Colombia
C3: Ingresos superiores a $500.000 | L3: subtotal en ventas | M3: subtotal nc en ventas
B4: no | C4: Concepto | D4: Tipo de documento | E4: Número identificación del informado | F4: Primer apellido del informado | G4: Segundo apellido del informado | H4: Primer nombre del informado | I4: Otros nombres del informado | J4: Razón social informado | K4: País de residencia o domicilio | L4: Ingresos brutos recibidos | M4: Devoluciones, rebajas y descuentos
B5: 1 | C5: 4001 | D5: 13 | E5: 1079940222 | F5: .CABALLERO | G5: MONTENEGRO | H5: JUAN | I5: MANUEL | K5: 169 | L5: 184874 | M5: =IFERROR(VLOOKUP(E5,nc_totalizada!$A$3:$D$156,3,0),0) -> 0
B6: 2 | C6: 4001 | D6: 13 | E6: 1079937378 | F6: .CANTILLO | G6: SANTOS | H6: JESUS | K6: 169 | L6: 168487 | M6: =IFERROR(VLOOKUP(E6,nc_totalizada!$A$3:$D$156,3,0),0) -> 0
B7: 3 | C7: 4001 | D7: 13 | E7: 30177198 | F7: .CASTRO | G7: MONTERO | H7: LUZ | K7: 169 | L7: 378151 | M7: =IFERROR(VLOOKUP(E7,nc_totalizada!$A$3:$D$156,3,0),0) -> 0
B8: 4 | C8: 4001 | D8: 13 | E8: 1079931569 | F8: .CRESPO | G8: VILLA | H8: CASILDA | K8: 169 | L8: 95444 | M8: =IFERROR(VLOOKUP(E8,nc_totalizada!$A$3:$D$156,3,0),0) -> 0
B9: 5 | C9: 4001 | D9: 13 | E9: 1004121069 | F9: .PASION | G9: MARTINEZ | H9: MARIA | I9: EUGENIA | K9: 169 | L9: 220402 | M9: =IFERROR(VLOOKUP(E9,nc_totalizada!$A$3:$D$156,3,0),0) -> 0
B10: 6 | C10: 4001 | D10: 13 | E10: 1004120997 | F10: .RODRIGUEZ | G10: RODRIGUEZ | H10: GLENDA | K10: 169 | L10: 100420 | M10: =IFERROR(VLOOKUP(E10,nc_totalizada!$A$3:$D$156,3,0),0) -> 0
B11: 7 | C11: 4001 | D11: 13 | E11: 22563210 | F11: ABDALA | G11: DE AVILA | H11: YULIETH | K11: 169 | L11: 33529 | M11: =IFERROR(VLOOKUP(E11,nc_totalizada!$A$3:$D$156,3,0),0) -> 0
B12: 8 | C12: 4001 | D12: 13 | E12: 1002302504 | F12: ACEVEDO | G12: MEZA | H12: LUZ | K12: 169 | L12: 300095 | M12: =IFERROR(VLOOKUP(E12,nc_totalizada!$A$3:$D$156,3,0),0) -> 0
B13: 9 | C13: 4001 | D13: 13 | E13: 1082844786 | F13: ACEVEDO | H13: YEISON | K13: 169 | L13: 90090 | M13: =IFERROR(VLOOKUP(E13,nc_totalizada!$A$3:$D$156,3,0),0) -> 0
B14: 10 | C14: 4001 | D14: 13 | E14: 1004122824 | F14: ACOSTA | G14: PALLARES | H14: CAROLINA | K14: 169 | L14: 72437 | M14: =IFERROR(VLOOKUP(E14,nc_totalizada!$A$3:$D$156,3,0),0) -> 0
B15: 11 | C15: 4001 | D15: 13 | E15: 1004123866 | F15: ACOSTA | G15: CANTILLO | H15: CESAR | I15: CAMILO | K15: 169 | L15: 103998 | M15: =IFERROR(VLOOKUP(E15,nc_totalizada!$A$3:$D$156,3,0),0) -> 0
B16: 12 | C16: 4001 | D16: 13 | E16: 1079911618 | F16: ACOSTA | H16: MARIA | I16: ELBIRA | K16: 169 | L16: 257187 | M16: =IFERROR(VLOOKUP(E16,nc_totalizada!$A$3:$D$156,3,0),0) -> 0
B17: 13 | C17: 4001 | D17: 13 | E17: 1079914290 | F17: ACOSTA | G17: PERTUZ | H17: LUZ | I17: NEIRA | K17: 169 | L17: 248097 | M17: =IFERROR(VLOOKUP(E17,nc_totalizada!$A$3:$D$156,3,0),0) -> 0
B18: 14 | C18: 4001 | D18: 13 | E18: 1079932236 | F18: ACOSTA | G18: MONTENEGRO | H18: NEIDER | K18: 169 | L18: 80234 | M18: =IFERROR(VLOOKUP(E18,nc_totalizada!$A$3:$D$156,3,0),0) -> 0
B19: 15 | C19: 4001 | D19: 13 | E19: 1079934441 | F19: ACOSTA | H19: YOLANDA | K19: 169 | L19: 172317 | M19: =IFERROR(VLOOKUP(E19,nc_totalizada!$A$3:$D$156,3,0),0) -> 0
B20: 16 | C20: 4001 | D20: 13 | E20: 1079935537 | F20: ACOSTA | G20: TORREJANO | H20: LUDYS | K20: 169 | L20: 95762 | M20: =IFERROR(VLOOKUP(E20,nc_totalizada!$A$3:$D$156,3,0),0) -> 0
B21: 17 | C21: 4001 | D21: 13 | E21: 1079941789 | F21: ACOSTA | G21: OSORIO | H21: AURA | K21: 169 | L21: 25612 | M21: =IFERROR(VLOOKUP(E21,nc_totalizada!$A$3:$D$156,3,0),0) -> 0
B22: 18 | C22: 4001 | D22: 13 | E22: 1082044949 | F22: ACOSTA | G22: VALLE | H22: YURANIS | K22: 169 | L22: 344538 | M22: =IFERROR(VLOOKUP(E22,nc_totalizada!$A$3:$D$156,3,0),0) -> 0
B23: 19 | C23: 4001 | D23: 13 | E23: 1082046200 | F23: ACOSTA | G23: VARELA | H23: WENDY | K23: 169 | L23: 248739 | M23: =IFERROR(VLOOKUP(E23,nc_totalizada!$A$3:$D$156,3,0),0) -> 0
B24: 20 | C24: 4001 | D24: 13 | E24: 1082046214 | F24: ACOSTA | H24: JESUS | K24: 169 | L24: 73109 | M24: =IFERROR(VLOOKUP(E24,nc_totalizada!$A$3:$D$156,3,0),0) -> 0
B25: 21 | C25: 4001 | D25: 13 | E25: 1127573690 | F25: ACOSTA | H25: MARIA | I25: ALEXANDRA | K25: 169 | L25: 48049 | M25: =IFERROR(VLOOKUP(E25,nc_totalizada!$A$3:$D$156,3,0),0) -> 0
B26: 22 | C26: 4001 | D26: 13 | E26: 1140849890 | F26: ACOSTA | H26: LILA | K26: 169 | L26: 41242 | M26: =IFERROR(VLOOKUP(E26,nc_totalizada!$A$3:$D$156,3,0),0) -> 0
B27: 23 | C27: 4001 | D27: 13 | E27: 1143138834 | F27: ACOSTA | G27: CAMARGO | H27: ENITH | K27: 169 | L27: 323409 | M27: =IFERROR(VLOOKUP(E27,nc_totalizada!$A$3:$D$156,3,0),0) -> 0
B28: 24 | C28: 4001 | D28: 13 | E28: 1151923 | F28: ACOSTA | G28: VACA | H28: JULIO | I28: CESAR | K28: 169 | L28: 1218487 | M28: =IFERROR(VLOOKUP(E28,nc_totalizada!$A$3:$D$156,3,0),0) -> 0
B29: 25 | C29: 4001 | D29: 13 | E29: 19863307 | F29: ACOSTA | G29: ESCORCHA | H29: LUISBETH | I29: YOHANA | K29: 169 | L29: 199814 | M29: =IFERROR(VLOOKUP(E29,nc_totalizada!$A$3:$D$156,3,0),0) -> 0
B30: 26 | C30: 4001 | D30: 13 | E30: 22638114 | F30: ACOSTA | G30: SANTODOMINGO | H30: CRISTINA | K30: 169 | L30: 51495 | M30: =IFERROR(VLOOKUP(E30,nc_totalizada!$A$3:$D$156,3,0),0) -> 0
B31: 27 | C31: 4001 | D31: 13 | E31: 26825760 | F31: ACOSTA | G31: OROZCO | H31: MAUDIS | K31: 169 | L31: 342419 | M31: =IFERROR(VLOOKUP(E31,nc_totalizada!$A$3:$D$156,3,0),0) -> 0
B32: 28 | C32: 4001 | D32: 13 | E32: 26881053 | F32: ACOSTA | H32: YESSICA | K32: 169 | L32: 30654 | M32: =IFERROR(VLOOKUP(E32,nc_totalizada!$A$3:$D$156,3,0),0) -> 0
B33: 29 | C33: 4001 | D33: 13 | E33: 32691267 | F33: ACOSTA | G33: BROCHERO | H33: LUZ | I33: MARINA | K33: 169 | L33: 697143 | M33: =IFERROR(VLOOKUP(E33,nc_totalizada!$A$3:$D$156,3,0),0) -> 0
B34: 30 | C34: 4001 | D34: 13 | E34: 57300706 | F34: ACOSTA | G34: YANCY | H34: EDITH | K34: 169 | L34: 1932773 | M34: =IFERROR(VLOOKUP(E34,nc_totalizada!$A$3:$D$156,3,0),0) -> 0
B35: 31 | C35: 4001 | D35: 13 | E35: 57305786 | F35: ACOSTA | G35: BOLAÑO | H35: JUANA | K35: 169 | L35: 503361 | M35: =IFERROR(VLOOKUP(E35,nc_totalizada!$A$3:$D$156,3,0),0) -> 0
B36: 32 | C36: 4001 | D36: 13 | E36: 57309594 | F36: ACOSTA | G36: BOLAÑO | H36: YULIS | I36: JOHANA | K36: 169 | L36: 579787 | M36: =IFERROR(VLOOKUP(E36,nc_totalizada!$A$3:$D$156,3,0),0) -> 0
B37: 33 | C37: 4001 | D37: 13 | E37: 1079936802 | F37: ACUNA | G37: JIMENEZ | H37: WENDY | K37: 169 | L37: 37461 | M37: =IFERROR(VLOOKUP(E37,nc_totalizada!$A$3:$D$156,3,0),0) -> 0
B38: 34 | C38: 4001 | D38: 13 | E38: 57307400 | F38: ACUNA | H38: AURA | I38: MARIA | K38: 169 | L38: 48721 | M38: =IFERROR(VLOOKUP(E38,nc_totalizada!$A$3:$D$156,3,0),0) -> 0
B39: 35 | C39: 4001 | D39: 13 | E39: 1010150212 | F39: ACUÑA | G39: MERCADO | H39: VANESA | K39: 169 | L39: 21008 | M39: =IFERROR(VLOOKUP(E39,nc_totalizada!$A$3:$D$156,3,0),0) -> 0
B40: 36 | C40: 4001 | D40: 13 | E40: 1081760820 | F40: ACUÑA | G40: MARTINEZ | H40: CELIA | K40: 169 | L40: 127259 | M40: =IFERROR(VLOOKUP(E40,nc_totalizada!$A$3:$D$156,3,0),0) -> 0
B41: 37 | C41: 4001 | D41: 13 | E41: 1082044435 | F41: ACUÑA | G41: DE LA MARCA | H41: ENA | K41: 169 | L41: 124184 | M41: =IFERROR(VLOOKUP(E41,nc_totalizada!$A$3:$D$156,3,0),0) -> 0
B42: 38 | C42: 4001 | D42: 13 | E42: 1083040780 | F42: ACUÑA | G42: GARIZADO | H42: MARIO | K42: 169 | L42: 40654 | M42: =IFERROR(VLOOKUP(E42,nc_totalizada!$A$3:$D$156,3,0),0) -> 0
B43: 39 | C43: 4001 | D43: 13 | E43: 39098545 | F43: ACUÑA | G43: CORTINA | H43: BELIA | K43: 169 | L43: 299239 | M43: =IFERROR(VLOOKUP(E43,nc_totalizada!$A$3:$D$156,3,0),0) -> 0
B44: 40 | C44: 4001 | D44: 13 | E44: 7598401 | F44: ACUÑA | G44: GIL | H44: YAMITH | K44: 169 | L44: 48319 | M44: =IFERROR(VLOOKUP(E44,nc_totalizada!$A$3:$D$156,3,0),0) -> 0
B45: 41 | C45: 4001 | D45: 13 | E45: 85433507 | F45: ACUÑA | G45: REYES | H45: GILBERTO | I45: JOSE | K45: 169 | L45: 1663882 | M45: =IFERROR(VLOOKUP(E45,nc_totalizada!$A$3:$D$156,3,0),0) -> 0
B46: 42 | C46: 4001 | D46: 13 | E46: 22636911 | F46: AFRICANO | G46: CHARRIZ | H46: NELIDA | K46: 169 | L46: 411261 | M46: =IFERROR(VLOOKUP(E46,nc_totalizada!$A$3:$D$156,3,0),0) -> 0
B47: 43 | C47: 4001 | D47: 13 | E47: 1193223497 | F47: AGUAS | G47: MARTINEZ | H47: BRIAN | I47: JOSE | K47: 169 | L47: 138235 | M47: =IFERROR(VLOOKUP(E47,nc_totalizada!$A$3:$D$156,3,0),0) -> 0
B48: 44 | C48: 4001 | D48: 13 | E48: 7142469 | F48: AGUIRRE | H48: ANIVAL | K48: 169 | L48: 57143 | M48: =IFERROR(VLOOKUP(E48,nc_totalizada!$A$3:$D$156,3,0),0) -> 0
B49: 45 | C49: 4001 | D49: 13 | E49: 1010126344 | F49: AHUMADA | G49: PAYAREZ | H49: JHONYS | K49: 169 | L49: 567479 | M49: =IFERROR(VLOOKUP(E49,nc_totalizada!$A$3:$D$156,3,0),0) -> 0
B50: 46 | C50: 4001 | D50: 13 | E50: 1081212482 | F50: AHUMADA | G50: ACOSTA | H50: DAIRO | I50: JOSE | K50: 169 | L50: 25276 | M50: =IFERROR(VLOOKUP(E50,nc_totalizada!$A$3:$D$156,3,0),0) -> 0
B51: 47 | C51: 4001 | D51: 13 | E51: 1083572468 | F51: AHUMADA | H51: KEVIN | K51: 169 | L51: 81513 | M51: =IFERROR(VLOOKUP(E51,nc_totalizada!$A$3:$D$156,3,0),0) -> 0
B52: 48 | C52: 4001 | D52: 13 | E52: 1084738629 | F52: AHUMADA | G52: NOGUERA | H52: YESENIA | I52: PAOLA | K52: 169 | L52: 58739 | M52: =IFERROR(VLOOKUP(E52,nc_totalizada!$A$3:$D$156,3,0),0) -> 0
B53: 49 | C53: 4001 | D53: 13 | E53: 9877508 | F53: AHUMADA | G53: CASTRO | H53: CESAR | K53: 169 | L53: 65084 | M53: =IFERROR(VLOOKUP(E53,nc_totalizada!$A$3:$D$156,3,0),0) -> 0
B54: 50 | C54: 4001 | D54: 13 | E54: 72334163 | F54: ALARCON | G54: POLO | H54: JAVIER | K54: 169 | L54: 873950 | M54: =IFERROR(VLOOKUP(E54,nc_totalizada!$A$3:$D$156,3,0),0) -> 0
B55: 51 | C55: 4001 | D55: 13 | E55: 1082849470 | F55: ALBORNOS | G55: CANTILLO | H55: ELSI | K55: 169 | L55: 297863 | M55: =IFERROR(VLOOKUP(E55,nc_totalizada!$A$3:$D$156,3,0),0) -> 0
B56: 52 | C56: 4001 | D56: 13 | E56: 84080740 | F56: ALCALA | H56: ALVARO | I56: MANUEL | K56: 169 | L56: 87863 | M56: =IFERROR(VLOOKUP(E56,nc_totalizada!$A$3:$D$156,3,0),0) -> 0
B57: 53 | C57: 4001 | D57: 13 | E57: 1000808352 | F57: ALDANA | G57: MARTINEZ | H57: LEONARDO | K57: 169 | L57: 51000 | M57: =IFERROR(VLOOKUP(E57,nc_totalizada!$A$3:$D$156,3,0),0) -> 0
B58: 54 | C58: 4001 | D58: 13 | E58: 57308029 | F58: ALDANA | G58: RODRIGUEZ | H58: ROXANA | K58: 169 | L58: 153932 | M58: =IFERROR(VLOOKUP(E58,nc_totalizada!$A$3:$D$156,3,0),0) -> 5462
B59: 55 | C59: 4001 | D59: 13 | E59: 1079938807 | F59: ALEJANDRO | G59: FONTALVO | H59: JOSE | K59: 169 | L59: 176471 | M59: =IFERROR(VLOOKUP(E59,nc_totalizada!$A$3:$D$156,3,0),0) -> 0
B60: 56 | C60: 4001 | D60: 13 | E60: 26814039 | F60: ALEMAN | G60: CANTILLO | H60: EDITH | K60: 169 | L60: 80588 | M60: =IFERROR(VLOOKUP(E60,nc_totalizada!$A$3:$D$156,3,0),0) -> 0
B61: 57 | C61: 4001 | D61: 13 | E61: 1079933355 | F61: ALFARO | G61: DE LA CRUZ | H61: MILENA | K61: 169 | L61: 280132 | M61: =IFERROR(VLOOKUP(E61,nc_totalizada!$A$3:$D$156,3,0),0) -> 0
B62: 58 | C62: 4001 | D62: 13 | E62: 1079912752 | F62: ALFONSO | G62: SILVA | H62: EMIL | K62: 169 | L62: 235294 | M62: =IFERROR(VLOOKUP(E62,nc_totalizada!$A$3:$D$156,3,0),0) -> 0
B63: 59 | C63: 4001 | D63: 13 | E63: 3741927 | F63: ALGARIN | G63: PALMA | H63: GABRIEL | K63: 169 | L63: 40924 | M63: =IFERROR(VLOOKUP(E63,nc_totalizada!$A$3:$D$156,3,0),0) -> 0
B64: 60 | C64: 4001 | D64: 13 | E64: 1079885053 | F64: ALMANZA | G64: RAMBAL | H64: ALDO | K64: 169 | L64: 73109 | M64: =IFERROR(VLOOKUP(E64,nc_totalizada!$A$3:$D$156,3,0),0) -> 0
B65: 61 | C65: 4001 | D65: 13 | E65: 1079938769 | F65: ALTAHONA | G65: CASTAÑEDA | H65: IVAN | I65: DAVID | K65: 169 | L65: 57899 | M65: =IFERROR(VLOOKUP(E65,nc_totalizada!$A$3:$D$156,3,0),0) -> 0
B66: 62 | C66: 4001 | D66: 13 | E66: 44150013 | F66: ALTAMAR | G66: MARENGO | H66: HANITH | K66: 169 | L66: 73848 | M66: =IFERROR(VLOOKUP(E66,nc_totalizada!$A$3:$D$156,3,0),0) -> 0
B67: 63 | C67: 4001 | D67: 13 | E67: 44160013 | F67: ALTAMAR | H67: HANITH | K67: 169 | L67: 49478 | M67: =IFERROR(VLOOKUP(E67,nc_totalizada!$A$3:$D$156,3,0),0) -> 0
B68: 64 | C68: 4001 | D68: 13 | E68: 26812747 | F68: ALVARADO | H68: FLORENZA | K68: 169 | L68: 75612 | M68: =IFERROR(VLOOKUP(E68,nc_totalizada!$A$3:$D$156,3,0),0) -> 0
B69: 65 | C69: 4001 | D69: 13 | E69: 32682473 | F69: ALVARADO | H69: GRACIELA | K69: 169 | L69: 31092 | M69: =IFERROR(VLOOKUP(E69,nc_totalizada!$A$3:$D$156,3,0),0) -> 0
B70: 66 | C70: 4001 | D70: 13 | E70: 57116296 | F70: ALVARADO | G70: VERGARA | H70: ROSA | I70: MARIA | K70: 169 | L70: 56200 | M70: =IFERROR(VLOOKUP(E70,nc_totalizada!$A$3:$D$156,3,0),0) -> 0
B71: 67 | C71: 4001 | D71: 13 | E71: 1004213282 | F71: ALVARES | G71: MANGA | H71: KEVIN | I71: ANDRES | K71: 169 | L71: 46200 | M71: =IFERROR(VLOOKUP(E71,nc_totalizada!$A$3:$D$156,3,0),0) -> 0
B72: 68 | C72: 4001 | D72: 13 | E72: 1073979146 | F72: ALVARES | H72: SHEIDY | K72: 169 | L72: 72521 | M72: =IFERROR(VLOOKUP(E72,nc_totalizada!$A$3:$D$156,3,0),0) -> 0
B73: 69 | C73: 4001 | D73: 13 | E73: 1079912370 | F73: ALVARES | G73: ACOSTA | H73: KELLIS | I73: JHOANA | K73: 169 | L73: 108133 | M73: =IFERROR(VLOOKUP(E73,nc_totalizada!$A$3:$D$156,3,0),0) -> 0
B74: 70 | C74: 4001 | D74: 13 | E74: 1082046215 | F74: ALVARES | G74: CASTRO | H74: KARINA | K74: 169 | L74: 199526 | M74: =IFERROR(VLOOKUP(E74,nc_totalizada!$A$3:$D$156,3,0),0) -> 0
B75: 71 | C75: 4001 | D75: 13 | E75: 1083572481 | F75: ALVARES | H75: CORALIS | K75: 169 | L75: 26891 | M75: =IFERROR(VLOOKUP(E75,nc_totalizada!$A$3:$D$156,3,0),0) -> 0
B76: 72 | C76: 4001 | D76: 13 | E76: 26881257 | F76: ALVARES | G76: MIRANDA | H76: OMAIRA | I76: LUZ | K76: 169 | L76: 870721 | M76: =IFERROR(VLOOKUP(E76,nc_totalizada!$A$3:$D$156,3,0),0) -> 0
B77: 73 | C77: 4001 | D77: 13 | E77: 1004122098 | F77: ALVAREZ | G77: PERALTA | H77: ARLEY | K77: 169 | L77: 29412 | M77: =IFERROR(VLOOKUP(E77,nc_totalizada!$A$3:$D$156,3,0),0) -> 0
B78: 74 | C78: 4001 | D78: 13 | E78: 1004122625 | F78: ALVAREZ | G78: ANDRADE | H78: KENDY | K78: 169 | L78: 50420 | M78: =IFERROR(VLOOKUP(E78,nc_totalizada!$A$3:$D$156,3,0),0) -> 0
B79: 75 | C79: 4001 | D79: 13 | E79: 1007162183 | F79: ALVAREZ | G79: MEDINA | H79: EBERTO | K79: 169 | L79: 387792 | M79: =IFERROR(VLOOKUP(E79,nc_totalizada!$A$3:$D$156,3,0),0) -> 0
B80: 76 | C80: 4001 | D80: 13 | E80: 1007162716 | F80: ALVAREZ | H80: TANIA | I80: MILENA | K80: 169 | L80: 331345 | M80: =IFERROR(VLOOKUP(E80,nc_totalizada!$A$3:$D$156,3,0),0) -> 0
B81: 77 | C81: 4001 | D81: 13 | E81: 1048210921 | F81: ALVAREZ | G81: DE LA HOZ | H81: LEONARDO | K81: 169 | L81: 546218 | M81: =IFERROR(VLOOKUP(E81,nc_totalizada!$A$3:$D$156,3,0),0) -> 0
B82: 78 | C82: 4001 | D82: 13 | E82: 1079912123 | F82: ALVAREZ | G82: VALENCIA | H82: ATILIO | I82: JOSE | K82: 169 | L82: 113763 | M82: =IFERROR(VLOOKUP(E82,nc_totalizada!$A$3:$D$156,3,0),0) -> 0
B83: 79 | C83: 4001 | D83: 13 | E83: 1079912658 | F83: ALVAREZ | G83: TORREGROZA | H83: LINA | K83: 169 | L83: 486687 | M83: =IFERROR(VLOOKUP(E83,nc_totalizada!$A$3:$D$156,3,0),0) -> 0
B84: 80 | C84: 4001 | D84: 13 | E84: 1079915043 | F84: ALVAREZ | G84: VALENCIA | H84: YOXANDRA | K84: 169 | L84: 591176 | M84: =IFERROR(VLOOKUP(E84,nc_totalizada!$A$3:$D$156,3,0),0) -> 0
B85: 81 | C85: 4001 | D85: 13 | E85: 1079934623 | F85: ALVAREZ | H85: JESITH | K85: 169 | L85: 47479 | M85: =IFERROR(VLOOKUP(E85,nc_totalizada!$A$3:$D$156,3,0),0) -> 0
B86: 82 | C86: 4001 | D86: 13 | E86: 1079937318 | F86: ALVAREZ | H86: MORELIA | K86: 169 | L86: 150694 | M86: =IFERROR(VLOOKUP(E86,nc_totalizada!$A$3:$D$156,3,0),0) -> 0
B87: 83 | C87: 4001 | D87: 13 | E87: 1082044068 | F87: ALVAREZ | H87: DANIEL | K87: 169 | L87: 58385 | M87: =IFERROR(VLOOKUP(E87,nc_totalizada!$A$3:$D$156,3,0),0) -> 0
B88: 84 | C88: 4001 | D88: 13 | E88: 1082045444 | F88: ALVAREZ | G88: PALLARES | H88: DANIELA | I88: MARIA | K88: 169 | L88: 29412 | M88: =IFERROR(VLOOKUP(E88,nc_totalizada!$A$3:$D$156,3,0),0) -> 0
B89: 85 | C89: 4001 | D89: 13 | E89: 1083572510 | F89: ALVAREZ | H89: JORGE | K89: 169 | L89: 49160 | M89: =IFERROR(VLOOKUP(E89,nc_totalizada!$A$3:$D$156,3,0),0) -> 0
B90: 86 | C90: 4001 | D90: 13 | E90: 19618617 | F90: ALVAREZ | G90: FONTALVO | H90: JULIO | I90: CESAR | K90: 169 | L90: 340336 | M90: =IFERROR(VLOOKUP(E90,nc_totalizada!$A$3:$D$156,3,0),0) -> 0
B91: 87 | C91: 4001 | D91: 13 | E91: 26881407 | F91: ALVAREZ | G91: TORREGROSA | H91: ELEDIS | I91: JUDITH | K91: 169 | L91: 32755 | M91: =IFERROR(VLOOKUP(E91,nc_totalizada!$A$3:$D$156,3,0),0) -> 0
B92: 88 | C92: 4001 | D92: 13 | E92: 36550688 | F92: ALVAREZ | G92: VALLE | H92: MARIA | K92: 169 | L92: 123613 | M92: =IFERROR(VLOOKUP(E92,nc_totalizada!$A$3:$D$156,3,0),0) -> 0
B93: 89 | C93: 4001 | D93: 13 | E93: 57305397 | F93: ALVAREZ | G93: CANTILLO | H93: CILIA | K93: 169 | L93: 25798 | M93: =IFERROR(VLOOKUP(E93,nc_totalizada!$A$3:$D$156,3,0),0) -> 0
B94: 90 | C94: 4001 | D94: 13 | E94: 7125976 | F94: ALVAREZ | H94: KEINER | K94: 169 | L94: 82377 | M94: =IFERROR(VLOOKUP(E94,nc_totalizada!$A$3:$D$156,3,0),0) -> 0
B95: 91 | C95: 4001 | D95: 13 | E95: 9877593 | F95: ALVAREZ | G95: POLO | H95: LEONARDO | I95: JOSE | K95: 169 | L95: 354472 | M95: =IFERROR(VLOOKUP(E95,nc_totalizada!$A$3:$D$156,3,0),0) -> 0
B96: 92 | C96: 4001 | D96: 13 | E96: 1047481782 | F96: ALVEA | H96: ITSVAN | K96: 169 | L96: 88805 | M96: =IFERROR(VLOOKUP(E96,nc_totalizada!$A$3:$D$156,3,0),0) -> 0
B97: 93 | C97: 4001 | D97: 13 | E97: 57290034 | F97: ALZATE | H97: ISAURA | K97: 169 | L97: 49394 | M97: =IFERROR(VLOOKUP(E97,nc_totalizada!$A$3:$D$156,3,0),0) -> 0
B98: 94 | C98: 4001 | D98: 13 | E98: 70257137 | F98: ALZATE | G98: MARIN | H98: CARLOS | I98: MARIO | K98: 169 | L98: 1271429 | M98: =IFERROR(VLOOKUP(E98,nc_totalizada!$A$3:$D$156,3,0),0) -> 0
B99: 95 | C99: 4001 | D99: 13 | E99: 1002072874 | F99: AMADOR | H99: SANTY | K99: 169 | L99: 75630 | M99: =IFERROR(VLOOKUP(E99,nc_totalizada!$A$3:$D$156,3,0),0) -> 0
B100: 96 | C100: 4001 | D100: 13 | E100: 1063081624 | F100: AMADOR | G100: ORTIZ | H100: DANIEL | K100: 169 | L100: 42521 | M100: =IFERROR(VLOOKUP(E100,nc_totalizada!$A$3:$D$156,3,0),0) -> 0
B101: 97 | C101: 4001 | D101: 13 | E101: 72269358 | F101: AMADOR | H101: RAFAEL | K101: 169 | L101: 121008 | M101: =IFERROR(VLOOKUP(E101,nc_totalizada!$A$3:$D$156,3,0),0) -> 0
...

Sheet nc_totalizada
A2: NIT Receptor | B2: Nombre Receptor | C2: subtotal | D2: iva
A3: 10010890 | B3: CARLOS SEPULVEDA | C3: 29412 | D3: 5588
A4: 1002134676 | B4: LAURA FLORES SALAS | C4: 28571 | D4: 5429
A5: 1003313999 | B5: CESAR MANUEL ROMERO MONTERO | C5: 1092437 | D5: 207563
A6: 1004120739 | B6: TONNY JAVIER ANDRADE MEJIA | C6: 66387 | D6: 12613
A7: 1004121396 | B7: JUAN DIEGO PABON | C7: 83007 | D7: 15759
A8: 1004123368 | B8: JULIETH CANO | C8: 503361 | D8: 95639
A9: 1004123373 | B9: MACIEL CANTILLO | C9: 24370 | D9: 4630
A10: 1004123442 | B10: CLAUDIA PEREZ CABALLERO | C10: 43697 | D10: 8303
A11: 1004123792 | B11: JESUS JOSE PEREZ | C11: 57143 | D11: 10857
A12: 1004212863 | B12: NAIROVIS GARCIA OLIVARES | C12: 49580 | D12: 9420
A13: 1004390016 | B13: ERIKA MONTENEGRO MONTERO | C13: 11765 | D13: 2235
A14: 1004434665 | B14: ALEJANDRA PEREZ ZABALETA | C14: 48740 | D14: 9261
... A156: 9876792 | B156: DOLSEY NAVARRO MONTENEGRO | C156: 285714 | D156: 54286
C158: =SUM(C3:C157) -> 27299061 | D158: =SUM(D3:D157) -> 5128758

Sheet 1008 OK
A2: 1008 | B2: Saldo de cuentas por cobrar al 31 de diciembre V7 | M2: 169 Colombia
A4: Concepto | B4: Tipo de documento | C4: Número identificación | D4: DV | E4: Primer apellido deudor | F4: Segundo apellido deudor | G4: Primer nombre deudor | H4: Otros nombres deudor | I4: Razón social deudor | J4: Dirección | K4: Código dpto. | L4: Código mcp | M4: País de residencia o domicilio | N4: Saldo cuentas por cobrar al 31-12

Sheet 1009 OK
A2: 1009 | B2: Saldo de cuentas por pagar al 31 de diciembre V7 | M2: 169 Colombia
A5: Concepto | B5: Tipo de documento | C5: Número identificación | D5: DV | E5: Primer apellido | F5: Segundo apellido | G5: Primer nombre | H5: Otros nombres | I5: Razón social | J5: Dirección | K5: Código dpto. | L5: Código mcp | M5: País de residencia o domicilio | N5: Saldo cuentas por pagar al 31-12

Sheet 1010
A1: 1010 | B1: Información de socios, accionistas, comuneros y/o cooperados V8 | N1: Patrimonio líquido
A2: En cuantía superior a tres millones de pesos ($3.000.000)
A3: Tipo de documento | B3: Número identificación socio o accionista | C3: DV | D3: Primer apellido socio o accionista | E3: Segundo apellido socio o accionista | F3: Primer nombre del socio o accionista | G3: Otros nombres socio o accionista | H3: Razón social | I3: Dirección | J3: Código dpto. | K3: Código mcp | L3: País de residencia o domicilio | M3: Valor patrimonial acciones o aportes al 31-12 | N3: Porcentaje de participación | O3: Porcentaje de participación (posición decimal)

Sheet 1012 OK
A1: 1012 | B1: Información de declaraciones tributarias, acciones y aportes, inversiones en bonos títulos valores y cuentas de ahorro y cuentas corrientes V7
J3: 169 Colombia
A4: Concepto | B4: Tipo de documento | C4: Número de Identificación | D4: DV | E4: Primer apellido del informado | F4: Segundo apellido del informado | G4: Primer nombre del informado | H4: Otros nombres del informado | I4: Razón social informado | J4: Pais de residencia o domicilio | K4: Valor al 31-12

Sheet 2276 0K
B1: 2276 | C1: Información de rentas de trabajo y pensiones V2
A3: Entidad Informante | B3: Tipo de documento del beneficiario | C3: Número de Identificación del beneficiario | D3: Primer Apellido del beneficiario | E3: Segundo Apellido del beneficiario | F3: Primer Nombre del beneficiario | G3: Otros Nombres del beneficiario | H3: Dirección del beneficiario | I3: Departamento del beneficiario | J3: Municipio del beneficiario | K3: País del beneficiario | L3: Pagos por Salarios | M3: Pagos por emolumentos eclesiásticos | N3: Pagos por honorarios | O3: Pagos por servicios | P3: Pagos por comisiones | Q3: Pagos por prestaciones sociales | R3: Pagos por viáticos | S3: Pagos por gastos de representación | T3: Pagos por compensaciones trabajo asociado cooperativo | U3: Otros pagos | V3: Pagos realizados con bonos electrónicos o de papel de servicio, cheques, tarjetas, vales, etc. | W3: Cesantías e intereses de cesantías efectivamente pagadas, consignadas o reconocidas en el periodo | X3: Pensiones de Jubilación, vejez o invalidez | Y3: Aportes Obligatorios por Salud | Z3: Aportes obligatorios a fondos de pensiones y solidaridad pensional y Aportes voluntarios al - RAIS | AA3: Aportes voluntarios a fondos de pensiones voluntarias | AB3: Aportes a cuentas AFC. | AC3: Valor de las retenciones en la fuente por pagos de rentas de trabajo o pensiones

Sheet 1004
A2: 1004 | B2: Descuentos tributarios solicitados V7
A4: Concepto | B4: Tipo de documento | C4: Número identificación | D4: Primer apellido | E4: Segundo apellido | F4: Primer nombre | G4: Otros nombres | H4: Razón social | I4: Dirección | J4: Código dpto. | K4: Código mcp | L4: Código pais | M4: Correo electrónico | N4: Valor del pago o abono en cuenta | O4: Valor del descuento tributario

Sheet 1011
A3: 1011 | B3: Información de las declaraciones tributarias V6
D6: Guía (No hace parte del reporte.)
A7: Concepto | B7: Saldos al -31-12
D8: 8104 | E8: Renta exenta por venta energía eléctrica generada con base en energía eólica, biomasa o residuos agrícolas, solar, geotérmica o de los mares. Art.235-2 numeral 3.
D9: 8106 | E9: Renta exenta por aprovechamiento de nuevas plantaciones forestales incluida la guadua el caucho y el marañón. Art. 235-2 numeral 5_x000D_
D10: 8109 | E10: Renta exenta por prestación de servicio de transporte fluvial con embarcaciones y planchones de bajo calado Art. 235-2 numeral 6.
D11: 8111 | E11: Rentas exentas por la utilidad en la enajenación de predios destinados a fines de utilidad pública. Num 9 Art. 207-2 E.T. Sentencia C-083 del 2018
D12: 8120 | E12: Rentas exentas por aplicación de algún convenio para evitar la doble tributación.
D13: 8121 | E13: Renta exenta por creaciones literarias dela economía naranja contenidas en el artículo 28 de la Ley 98 de 1993. Art. 235-2 numeral 8.
D14: 8125 | E14: Rentas exentas por Intereses, comisiones y pagos por deuda pública externa, E.T. art. 218 E.T.
D15: 8127 | E15: Rentas exentas por inversión en nuevos aserríos, plantas de procesamiento y plantaciones de árboles maderables y árboles en producción de frutos. E.T., art. 235-2, numeral 5.
D16: 8133 | E16: Rentas exentas por servicios prestados en hoteles nuevos. E.T., Art. 207-2, Num 3 Sentencia C 235 del 29 de mayo de 2019
D17: 8134 | E17: Rentas exentas por servicios prestados en hoteles remodelado y/o ampliados. E.T., Art. 207-2 E.T, Num. 4. Sentencia C 235 del 29 de mayo de 2019
D18: 8140 | E18: Rentas exentas por aportes voluntarios a los fondos de pensiones. E.T. art. 126-1, inc. 2
D19: 8141 | E19: Rentas exentas por los ahorros a largo plazo para el fomento de la construcción. E.T., art. 126-4.
... D167: 9210 | E167: Exención en IVA Las bicicletas y sus partes; motocicletas y sus partes y motocarros y sus partes, que se introduzcan y comercialicen en los departamentos de Amazonas, Guainía, Guaviare, Vaupés y Vichada, siempre y cuando se destinen exclusivamente al consumo dentro del mismo departamento. Numeral 6 del art. 477 del E.T.

Sheet 1647 
A2: 1647 | B2: Ingresos recibidos para terceros V2
A3: Sin cuantias minimas | J3: 169 Colombia | X3: 169 Colombia
A4: Concepto | B4: Tipo de documento de quien se recibe el ingreso | C4: Número identificación de quien recibe el ingreso | D4: DV | E4: Primer apellido de quien se recibe el ingreso | F4: Segundo apellido de quien se recibe el ingreso | G4: Primer nombre de quien se recibe el ingreso | H4: Otros nombres de quien se recibe el ingreso | I4: Razón social de quien se recibe el ingreso | J4: País de residencia o domicilio de quien se recibe el ingreso | K4: Valor total de la operación | L4: Valor ingreso reintegrado transferido distribuido al tercero | M4: Valor retención reintegrada transferida distribuida al tercero | N4: Tipo de documento del tercero para quien se recibió el ingreso | O4: Identificación del tercero para quien se recibió el ingreso | P4: Primer apellido del tercero para quien se recibió el ingreso | Q4: Segundo apellido del tercero par quien se recibió el ingreso | R4: Primer nombre del tercero para quien se recibió el ingreso | S4: Otros nombres del tercero para quien se recibió el ingreso | T4: Razón social del tercero para quien se recibió el ingreso | U4: Dirección | V4: Código dpto. | W4: Código mcp | X4: País de residencia o domicilio

Sheet 2275
A2: 2275 | B2: Ingresos no constitutivos de renta ni ganancia ocasional V1
A4: Concepto | B4: Tipo de documento del tercero | C4: Número identificación del tercero | D4: Primer apellido del informado | E4: Segundo apellido del informado | F4: Primer nombre del informado | G4: Otros nombres del informado | H4: Razón social | I4: Dirección | J4: Código dpto. | K4: Código mcp | L4: Código País | M4: Correo electrónico | N4: Valor total del ingreso | O4: Valor del ingreso no constitutivo de renta ni ganancia ocasional solicitado

Sheet 2280
A1: 2280 | B1: Deducción empleadas victimas de la violencia V1
A3: Tipo de documento empleada | B3: Número identificación empleada | C3: Primer apellido | D3: Segundo apellido | E3: Primer nombre | F3: Otros nombres | G3: Fecha inicio contrato | H3: Fecha final contrato | I3: Tipo medida certificación | J3: Cargo contratado | K3: Salario pagados durante el periodo | L3: Prestaciones sociales pagados durante el periodo | M3: Edad mujer contratada | N3: Nivel educativo

Sheet 1036
A1: 1036 | B1: Información de subordinadas o vinculadas del exterior V8
I2: 169 Colombia
A3: Tipo de informante | B3: Identificación de la subordinada o vinculada | C3: Razón social de la subordinada o vinculada | D3: País de la subordinada o vinculada | E3: Vehiculo de inversión | F3: Forma de control | G3: Tipo de control | H3: Participación en el capital de la subordinada o vinculada | I3: Participación en los resultados de la subordinada o vinculada

Sheet 1035
A1: 1035 | B1: Entidades subordinadas o controladas nacionales V7
A3: Tipo de documento | B3: Identificación de la subordinada | C3: Primer apellido del informado | D3: Segundo apellido del informado | E3: Primer nombre del informado | F3: Otros nombres del informado | G3: Razón social de la subordinada | H3: Dirección | I3: Código dpto. | J3: Código mcp | K3: Vehiculo de inversión | L3: Forma de control | M3: Tipo de control | N3: Participación en el capital de la subordinada o vinculada | O3: Participación en los resultados de la subordinada o vinculada

Sheet 1034
A3: 1034 | B3: Información de estados financieros consolidados- Grupos economicos V6
A4: Las entidades que en aplicación de las normas de contabilidad e información financiera vigentes en Colombia se encuentren en la obligación de preparar y difundir estados inancieros consolidados.
A7: Concepto | B7: Valor contable al -31-12

Sheet 5253
A1: 5253 | B1: Información de beneficiarios efectivos V1
A2: Las sociedades colombianas que sean subsidiarias o filiales de sociedades nacionales o del exterior, establecimientos permanentes de empresas del exterior, | J2: 169 Colombia
A3: Tipo de informante | B3: Tipo de documento | C3: Número identificación | D3: Primer apellido del informado | E3: Segundo apellido del informado | F3: Primer nombre del informado | G3: Otros nombres del informado | H3: Fecha de nacimiento | I3: País de nacionalidad | J3: País de residencia o domicilio | K3: Fecha final como beneficiario efectivo

Sheet 2575
A1: 2575 | B1: Donaciones recibidas y certificadas por entidades no contribuyentes V1
A3: Forma de donación | B3: Monto de la donación | C3: Tipo de persona donante | D3: Tipo de documento | E3: Número identificación | F3: Primer apellido del informado | G3: Segundo apellido del informado | H3: Primer nombre del informado | I3: Otros nombres del informado | J3: Razón social

Sheet Control
A2: Envio | B2: Formato | C2: Version | D2: Registros
A3: 1
A4: 2
A5: 3
A6: 4
A7: 5
A8: 6
A9: 7
A10: 8
A11: 9
A12: 10
A13: 11
A14: 12
A15: 13

Sheet Info
B3: PAISES | E3: DEPARTAMENTOS | H3: TIPO DE DOCUMENTOS
B4: 013 | C4: AFGANISTAN | E4: 91 | F4: Amazonas | H4: 11 | I4: Registro civil de nacimiento
B5: 017 | C5: ALBANIA | E5: 05 | F5: Antioquia | H5: 12 | I5: Tarjeta de identidad
B6: 023 | C6: ALEMANIA | E6: 81 | F6: Arauca | H6: 13 | I6: Cédula de ciudadanía
B7: 037 | C7: ANDORRA | E7: 08 | F7: Atlántico | H7: 21 | I7: Tarjeta de extranjería
B8: 040 | C8: ANGOLA | E8: 11 | F8: Bogotá D.C. | H8: 22 | I8: Cédula de extranjería
B9: 041 | C9: ANGUILLA | E9: 13 | F9: Bolívar | H9: 31 | I9: Nit
B10: 043 | C10: ANTIGUA Y BARBUDA | E10: 15 | F10: Boyacá | H10: 41 | I10: Pasaporte
B11: 047 | C11: ANTILLAS HOLANDESAS | E11: 17 | F11: Caldas | H11: 42 | I11: Tipo de documento Extranjero
B12: 053 | C12: ARABIA SAUDITA | E12: 18 | F12: Caquetá | H12: 43 | I12: Sin identificación del exterior o para uso definido por la DIAN
B13: 059 | C13: ARGELIA | E13: 85 | F13: Casanare
B14: 063 | C14: ARGENTINA | E14: 19 | F14: Cauca
B15: 026 | C15: ARMENIA | E15: 20 | F15: Cesar
B16: 027 | C16: ARUBA | E16: 27 | F16: Chocó
B17: 069 | C17: AUSTRALIA | E17: 23 | F17: Córdoba
B18: 072 | C18: AUSTRIA | E18: 25 | F18: Cundinamarca
B19: 074 | C19: AZERBAIJAN | E19: 94 | F19: Guainía
B20: 077 | C20: BAHAMAS | E20: 95 | F20: Guaviare
B21: 080 | C21: BAHREIN | E21: 41 | F21: Huila
B22: 081 | C22: BANGLADESH | E22: 4+E224 | F22: La Guajira
B23: 083 | C23: BARBADOS | E23: 47 | F23: Magdalena
B24: 087 | C24: BELGICA | E24: 50 | F24: Meta
... B26: 091 | C26: BELORUS | E26: 54 | F26: Norte de Santander
B27: 229 | C27: BENIN | E27: 86 | F27: Putumayo
B28: 090 | C28: BERMUDAS | E28: 63 | F28: Quindío
B29: 093 | C29: BIRMANIA (MYANMAR) | E29: 66 | F29: Risaralda
B30: 097 | C30: BOLIVIA | E30: 88 | F30: San Andrés
B31: 029 | C31: BOSNIA-HERZEGOVINA | E31: 68 | F31: Santander
B32: 101 | C32: BOTSWANA | E32: 70 | F32: Sucre
B33: 105 | C33: BRASIL | E33: 73 | F33: Tolima
B34: 108 | C34: BRUNEI DARUSSALAM | E34: 76 | F34: Valle del Cauca
B35: 111 | C35: BULGARIA | E35: 97 | F35: Vaupés
B36: 031 | C36: BURKINA FASSO | E36: 99 | F36: Vichada
B37: 115 | C37: BURUNDI
B38: 119 | C38: BUTAN
B39: 127 | C39: CABO VERDE
B40: 137 | C40: CAIMAN, ISLAS
B41: 145 | C41: CAMERUN, REPUBLICA U
B42: 149 | C42: CANADA
B43: 155 | C43: CANAL(NORMANDAS),ISL
B44: 157 | C44: CANTON ENDERBURY,ISL
B45: 203 | C45: CHAD
B46: 211 | C46: CHILE
B47: 215 | C47: CHINA
B48: 221 | C48: CHIPRE
... B107: 375 | C107: IRLANDA (EIRE)
B108: 033 | C108: ISLA DE MAN
B109: 379 | C109: ISLANDIA
B110: 566 | C110: ISLAS MENORES DE ESTADOS UNIDOS
B111: 383 | C111: ISRAEL
B112: 386 | C112: ITALIA
B113: 391 | C113: JAMAICA
B114: 399 | C114: JAPON
B115: 395 | C115: JOHNSTON,ISLA
B116: 403 | C116: JORDANIA
B117: 141 | C117: KAMPUCHEA (CAMBOYA)
B118: 406 | C118: KAZAJSTAN
B119: 410 | C119: KENYA
B120: 412 | C120: KIRGUIZISTAN
... B162: 531 | C162: NIUE, ISLA
B163: 001 | C163: NIVE ISLA
B164: 999 | C164: NO DECLARADOS
B165: 535 | C165: NORFOLK, ISLA
B166: 538 | C166: NORUEGA
B167: 542 | C167: NUEVA CALEDONIA
B168: 548 | C168: NUEVA ZELANDIA
B169: 556 | C169: OMAN
B170: 573 | C170: PAISES BAJOS(HOLANDA
B171: 576 | C171: PAKISTAN
B172: 578 | C172: PALAU, ISLAS
B173: 579 | C173: PALESTINA
B174: 580 | C174: PANAMA
B175: 545 | C175: PAPUASIA NUEV GUINEA
... B204: 728 | C204: SENEGAL
B205: 032 | C205: SERBIA
B206: 731 | C206: SEYCHELLES
B207: 735 | C207: SIERRA LEONA
B208: 741 | C208: SINGAPUR
B209: 744 | C209: SIRIA,REPUBLICA ARAB
B210: 748 | C210: SOMALIA
B211: 750 | C211: SRI LANKA
B212: 756 | C212: SUDAFRICA,REPUBLICA
B213: 759 | C213: SUDAN
B214: 764 | C214: SUECIA
B215: 767 | C215: SUIZA
B216: 770 | C216: SURINAM
B217: 773 | C217: SWAZILANDIA
... B249: 897 | C249: ZONA NEUTRAL(PALESTA

Sheet clientes
A1: nit | B1: direccion | C1: dpto | D1: ciudad | E1: dpto | F1: munic | G1: tipo_doc | H1: razon | I1: nombre1 | J1: NOMBRE2 | K1: apellido1 | L1: apellido2
A2: 900276962 | B2: Cra. 52 # 70 - 168 | C2: Atlántico | D2: Barranquilla | E2: 08 | F2: 001 | G2: 31 | H2: D1 S A S
A3: 901873198 | B3: Cl. 116 #42b 91 | C3: Atlántico | D3: Puerto Colombia | E3: 08 | F3: 573 | G3: 31 | H3: FERRETERIA PONQUIFON SEDE 93
A4: 32826857 | B4: Cra. 51B #106-200 | C4: Atlántico | D4: Barranquilla | E4: 08 | F4: 001 | G4: 13 | I4: MARENA | K4: DE LA ROSA | L4: NIEBLES
A5: 800051755 | B5: Calle 66 Vía 40, Esquina | C5: Atlántico | D5: Barranquilla | E5: 08 | F5: 001 | G5: 31 | H5: NULE MARINO & COMPAÑIA SAS
A6: 800165377 | B6: Carrera 51B #93-119 | C6: Atlántico | D6: Barranquilla | E6: 08 | F6: 001 | G6: 31 | H6: GRUPO DECOR S.A.S.
A7: 800165720 | B7: Carrera 41 No. 46 - 137 | C7: Atlántico | D7: Barranquilla | E7: 08 | F7: 001 | G7: 31 | H7: ALCANTARA ASOCIADOS S.A.S.
A8: 800165815 | B8: Cra. 56 #5c - 50, | C8: Cundinamarca | D8: Bogotá | E8: 11 | F8: 001 | G8: 31 | H8: TEXTILES 1 x 1 SAS
A9: 800242106 | B9: Cra. 53 #98-2 | C9: Atlántico | D9: Barranquilla | E9: 08 | F9: 001 | G9: 31 | H9: SODIMAC COLOMBIA S.A.
A10: 802002267 | B10: CALLE 77 B CR 59 61 OF1002 | C10: Atlántico | D10: Barranquilla | E10: 08 | F10: 001 | G10: 31 | H10: TEXVIGAR S.A.S.
A11: 802003599 | B11: Cl. 44 #43-115 | C11: Atlántico | D11: Barranquilla | E11: 08 | F11: 001 | G11: 31 | H11: DISNAR S.A.S - VILLA CAMPESTRE
A12: 802004266 | B12: Carrera 43 #80-120. | C12: Atlántico | D12: Barranquilla | E12: 08 | F12: 001 | G12: 31 | H12: FERRETERIA METROPOLIS S.A.S.
A13: 802006391 | B13: Cra. 51 #76 - 47 | C13: Atlántico | D13: Barranquilla | E13: 08 | F13: 001 | G13: 31 | H13: CREPES CARIBE S.A.
A14: 802017066 | B14: Carrera 38 No. 69D - 29 | C14: Atlántico | D14: Barranquilla | E14: 08 | F14: 001 | G14: 31 | H14: SODICSA S.A.S
A15: 802023507 | B15: Carrera 43 # 9-97, Local 42, 43, 44 y 45 | C15: Atlántico | D15: Barranquilla | E15: 08 | F15: 001 | G15: 31 | H15: CONNY DE LA COSTA S.A.S.
A16: 811009788 | B16: Cl. 84b #38 - 11 | C16: Atlántico | D16: Barranquilla | E16: 08 | F16: 001 | G16: 31 | H16: DISTRACOM S.A.
... A25: 860503159 | B25: Carrera 53 No. 94-50, Local 3 | C25: Atlántico | D25: Barranquilla | E25: 08 | F25: 001 | G25: 31 | H25: PASH S.A.S
A26: 8674041 | B26: Calle 54 No. 42-15 | C26: Atlántico | D26: Barranquilla | E26: 08 | F26: 001 | G26: 13 | I26: ENRIQUE | J26: RICARDO | K26: HENRIQUEZ | L26: ARAZO
A27: 890102010 | B27: Cra. 53 #106 - 280 | C27: Atlántico | D27: Barranquilla | E27: 08 | F27: 001 | G27: 31 | H27: CAMARA DE COMERCIO DE BARRANQUILLA
A28: 890102603 | B28: Cra. 38 #36-02 | C28: Atlántico | D28: Barranquilla | E28: 08 | F28: 001 | G28: 31 | H28: GRUPO MI CORRAL S.A
A29: 890115118 | B29: Cra. 38 #36-02 | C29: Atlántico | D29: Barranquilla | E29: 08 | F29: 001 | G29: 31 | H29: FRENOS BARRANQUILLA SAS
A30: 890115294 | B30: Cra. 55 #99 51 | C30: Atlántico | D30: Barranquilla | E30: 08 | F30: 001 | G30: 31 | H30: HOT AMERICA`S FAVORITE PIZZA S.A.S
A31: 890900943 | B31: Calle 98 # 51B - 91 | C31: Atlántico | D31: Barranquilla | E31: 08 | F31: 001 | G31: 31 | H31: COLOMBIANA DE COMERCIO S.A.
A32: 900021337 | B32: Calle 40 No. 44-39, Oficina 6H | C32: Atlántico | D32: Barranquilla | E32: 08 | F32: 001 | G32: 31 | H32: CREDISEGUROS DE LA COSTA LTDA
A33: 900059238 | B33: Cra. 51B #106-200 | C33: Atlántico | D33: Barranquilla | E33: 08 | F33: 001 | G33: 31 | H33: MAKRO SUPERMAYORISTA S.A.S
A34: 900214193 | B34: CALLE 110 43 C 735 | C34: Atlántico | D34: Barranquilla | E34: 08 | F34: 001 | G34: 31 | H34: INVERSIONES COMBGAS S.A.S
A35: 900230625 | B35: Carrera 43 # 82-09 | C35: Atlántico | D35: Barranquilla | E35: 08 | F35: 001 | G35: 31 | H35: ESTACION DE SERVICIO COLISEO S.A
A36: 900276962 | B36: Cra. 52 # 70 - 168 | C36: Atlántico | D36: Barranquilla | E36: 08 | F36: 001 | G36: 31 | H36: D1 S A S
A37: 900309367 | B37: CALLE 1 #10-50 LTE | C37: Atlántico | D37: Barranquilla | E37: 08 | F37: 001 | G37: 31 | H37: SANTA MARIA DEL MAR S.A.S
A38: 900319753 | B38: Carrera 53 con calle 106 esquina | C38: Atlántico | D38: Barranquilla | E38: 08 | F38: 001 | G38: 31 | H38: PRICESMART COLOMBIA S.A.S.
... A121: 800098601 | B121: Via 40 60 180 Sec La Loma 3 | C121: Atlántico | D121: BARRANQUILLA | E121: 08 | F121: 001 | G121: 31 | H121: UNIFEL S.A.
A122: 79148397 | B122: CL 10 20 35 OF 295 | C122: BOGOTÁ D.C | D122: Bogotá | E122: 11 | F122: 001 | G122: 13 | I122: JUAN | J122: CARLOS | K122: MOJOCOA | L122: PARADA
A123: 10934103 | B123: CL 36 1 91 BRR CENTRO | C123: Córdoba | D123: Montería | E123: 23 | F123: 001 | G123: 13 | I123: LUIS | J123: CARLOS | K123: CORREA | L123: CASTRO
A124: 43785419 | B124: CL 465 54 24 | C124: Antioquia | D124: Medellín | E124: 05 | F124: 001 | G124: 13 | I124: MARIA | J124: FLORELBA | K124: GALLEGO | L124: GOMEZ
A125: 70696078 | B125: CL 465 54 24 | C125: Antioquia | D125: Medellín | E125: 05 | F125: 001 | G125: 13 | I125: WILLIAM | J125: DARIO | K125: GALLEGO | L125: GOMEZ
A126: 70353742 | B126: CL 8 14 15 | C126: Córdoba | D126: CIENAGA DE ORO | E126: 23 | F126: 189 | G126: 13 | I126: JOHNY | J126: ANDRES | K126: GIRALDO | L126: MARIN
A127: 1124060096 | B127: CR 52 A 45 33 | C127: Antioquia | D127: Medellín | E127: 05 | F127: 001 | G127: 13 | I127: RABIH | K127: SERHAN | L127: TOUFIC
A128: 9868376 | B128: CL 36 2 42 P 1 Lc 1 | C128: Cordoba | D128: Monteria | E128: 23 | F128: 001 | G128: 13 | I128: FRANK | J128: FERNANDO | K128: ZULUAGA | L128: SANCHEZ
A129: 13745511 | B129: CL 4 6 33 CRR LA LOMA | C129: Cesar | D129: El Paso | E129: 20 | F129: 250 | G129: 13 | I129: RUFINO | K129: PARDO | L129: MILLAN
A130: 70725876 | B130: Cra 2 36 35 | C130: Cordoba | D130: Monteria | E130: 23 | F130: 001 | G130: 13 | I130: EFREN | J130: DE JESUS | K130: LOPEZ | L130: VALENCIA
A131: 98483586 | B131: Carrera 65 N 74 75 Bodega 117 | C131: MEDELLIN | D131: Antioquia | E131: 05 | F131: 001 | G131: 13 | I131: FABIAN | K131: VALENCIA | L131: GARRO
A132: 1022358313 | B132: CL 10 12 224 Lc 120 | C132: BOGOTÁ D.C | D132: Bogotá | E132: 11 | F132: 001 | G132: 13 | I132: CESAR | J132: ALDRIN | K132: ACUA | L132: RODRIGUEZ
A133: 1063169167 | B133: CL 17 A 14 50 BRR SAN FRANCISCO | C133: Cordoba | D133: Lorica | E133: 23 | F133: 417 | G133: 13 | I133: LINA | J133: MARIA | K133: PADILLA | L133: NAVAJA
A134: 1129485999 | B134: CRA 21 21 04 | C134: Antioquia | D134: San Luis | E134: 05 | F134: 660 | G134: 13 | I134: ROSA | J134: MARIA | K134: FONSECA | L134: JIMENEZ
A135: 901572689 | B135: CENTRO COMERCIAL LOS EJECUTIVOS OFC 27B | D135: Cartagena | E135: 13 | F135: 001 | G135: 31 | H135: CREANDO SOLUCIONES FINANCIERAS S.A.S.
A136: 901971176 | B136: BRR DIVINO NIÑO CRR LOMA | D136: El Paso | E136: 20 | F136: 250 | G136: 31 | H136: A/C MAX MULTISERVICIOS SAS
A137: 900187601 | B137: CL 36 SUR 22 138 IN 21 | D137: Envigado | E137: 05 | F137: 266 | G137: 31 | H137: AGROSERVICIOS SAN SIMON S.A.S
A138: 901334751 | B138: CL 98 64 120 | D138: Barranquilla | E138: 08 | F138: 001 | G138: 31 | H138: ALCOCER CONSTRUCIONES SAS
A139: 901244033 | B139: BRR TERRAZAS DE CALICANTO TO 8 AP 901 | D139: Cartagena | E139: 13 | F139: 001 | G139: 31 | H139: ALIMENTOS PREMIUM DEL CARIBE SAS
A140: 830513773 | B140: DG CL 71 BIS 20 69 | D140: Bogota D.C. | E140: 11 | F140: 001 | G140: 31 | H140: APPLUS NORCONTROL COLOMBIA LIMITADA
A141: 901281228 | B141: CR 14W N 17-53 | D141: Montería | E141: 23 | F141: 001 | G141: 31 | H141: ARKOOS ARQUITECTURA Y CONSTRUCCIONES SAS
A142: 901281229 | B142: CR 14W N 17 53 | D142: Montería | E142: 23 | F142: 001 | G142: 31 | H142: ARKOOS ARQUITECTURA Y CONSTRUCCIONES SAS
A143: 901651878 | B143: cr 25 46 15 | D143: Barranquilla | E143: 08 | F143: 001 | G143: 31 | H143: ARN INGENIERIA SAS
A144: 901661340 | B144: CR 14W N 17-59 | D144: Montería | E144: 23 | F144: 001 | G144: 31 | H144: ARQCICOM SAS
A145: 830077126 | B145: CR 83 23B 55 | D145: Bogota D.C. | E145: 11 | F145: 001 | G145: 31 | H145: ARQUITECTURA INGENIERIA Y DESARROLO SAS
A146: 901999162 | B146: BRR LA ESPERANZA CRR la loma | D146: El Paso | E146: 20 | F146: 250 | G146: 31 | H146: AUTOPARTES CALA VILLAMIL S.A.S
... A254: 900216620 | B254: CR 12 1 | D254: Valledupar | E254: 20 | F254: 001 | G254: 31 | H254: VIVIRMEJOR SERVICIOS S.A.S
A255: 2759236 | B255: BRR LOS ANGELES CL 4 | D255: Ciénaga De Oro | E255: 23 | F255: 189 | G255: 13 | I255: GUILLERMO | J255: ANDRES | K255: SANCHEZ | L255: MARTINEZ
A256: 2759873 | B256: CL 6 5 A 36 BRR SAN JOSE | D256: Ciénaga De Oro | E256: 23 | F256: 189 | G256: 13 | I256: EDINSON | K256: MESTRA | L256: ZAPA
A257: 2760456 | B257: cr 3 65 07 | D257: Montería | E257: 23 | F257: 001 | G257: 13 | I257: ANGEL | J257: JAVIER | K257: ARGUMEDO | L257: BEDOYA
A258: 6880812 | B258: CL 67 2 67 BRR RECREO | D258: Montería | E258: 23 | F258: 001 | G258: 13 | I258: ADOLFO | J258: ANTONIO | K258: JALLER | L258: CABALLERO
A259: 6894855 | B259: cr 3 65 07 | D259: Montería | E259: 23 | F259: 001 | G259: 13 | I259: JADER | J259: EDUARDO | K259: SOLANO | L259: FLOREZ
A260: 10774495 | B260: KM 15 VIA CERETE | D260: Ciénaga De Oro | E260: 23 | F260: 189 | G260: 13 | I260: MARCO | J260: ANTONIO | K260: DELGADO | L260: JIMENEZ
A261: 10775954 | B261: cr 4 N 32 38 | D261: Montería | E261: 23 | F261: 001 | G261: 13 | I261: ENRIQUE | J261: RAFAEL | K261: GARCIA | L261: JULIO
A262: 10892857 | B262: BRR JUAN VEINTI TRES | D262: Pueblo Nuevo | E262: 23 | F262: 570 | G262: 13 | I262: ALEJANDRO | J262: JOSE | K262: MARTINEZ | L262: URANGO
A263: 19386534 | B263: CR 46 80 173 | D263: Barranquilla | E263: 08 | F263: 001 | G263: 13 | I263: ALONSO | J263: DE JESUS | K263: USTA | L263: CHICA
A264: 19596644 | B264: CL 10 18 82 | D264: El Paso | E264: 20 | F264: 250 | G264: 13 | I264: JOHNELKIN | K264: FONSECA | L264: FRANCIA
A265: 25870082 | B265: CR 25 2 A 20 SANISIDRO | D265: Ciénaga De Oro | E265: 23 | F265: 189 | G265: 13 | I265: MARIA | J265: DEL SOCORRO | K265: DURANGO | L265: PADILLA
A266: 25872399 | B266: cll 6 cr6 brr cartagenita | D266: Ciénaga De Oro | E266: 23 | F266: 189 | G266: 13 | I266: RUTH | J266: MARY | K266: CALUME | L266: FUENTES
A267: 25873522 | B267: CL 2 CR 18 BRR LAS COLINAS | D267: Ciénaga De Oro | E267: 23 | F267: 189 | G267: 13 | I267: SHIRLE | J267: SUSANA | K267: BARON | L267: FLOREZ
A268: 25878948 | B268: CORR LAS BALSAS | D268: Ciénaga De Oro | E268: 23 | F268: 189 | G268: 13 | I268: MARIA | J268: DEL CARMEN | K268: DIAZ | L268: MESTRA
A269: 43085326 | B269: CL 62 a 25 larga | D269: Ciénaga De Oro | E269: 23 | F269: 189 | G269: 13 | I269: CLAUDIA | J269: PATRICIA | K269: ROLDAN | L269: CALLE
A270: 43729956 | B270: cll 66 4 89 | D270: Montería | E270: 23 | F270: 001 | G270: 13 | I270: CLAUDIA | J270: CECILIA | K270: ANAYA | L270: HOYOS
A271: 49556514 | B271: BRR NOVENA BATALLA MANZ 3 | D271: Curumani | E271: 20 | F271: 228 | G271: 13 | I271: CECILIA | K271: ORTEGA | L271: PALACIO
A272: 49778969 | B272: BRR LAS VACAS CORR LA LOMA | D272: El Paso | E272: 20 | F272: 250 | G272: 13 | I272: ANA | J272: GREGORIA | K272: AVILA | L272: LASCANO
A273: 49793905 | B273: CALLE 10 13A 17 | D273: El Paso | E273: 20 | F273: 250 | G273: 13 | I273: BRAICY | K273: SERPA | L273: PEDROZ
A274: 50954243 | B274: CL 57 10 60 CA 35 | D274: Montería | E274: 23 | F274: 001 | G274: 13 | I274: PAULETH | J274: PAOLA | K274: PASTRANA | L274: PACHECO
A275: 52269174 | B275: CL 65A 27 59 AP 501 | D275: Bogota D.C. | E275: 11 | F275: 001 | G275: 13 | I275: OLGA | J275: LUCIA | K275: TORRES | L275: CAMARGO
A276: 78035402 | B276: CR 15 53 27 T2 AP 202 VALLEJUELOS | D276: Montería | E276: 23 | F276: 001 | G276: 13 | I276: CESAR | J276: AUGUSTO | K276: ARCIA | L276: LAFONT
A277: 78035439 | B277: CL 7 17 35 | D277: Ciénaga De Oro | E277: 23 | F277: 189 | G277: 13 | I277: ALDO | J277: GREGORIO | K277: BURGOS | L277: ALVAREZ
A278: 78037607 | B278: CL 10 4 26 | D278: Ciénaga De Oro | E278: 23 | F278: 189 | G278: 13 | I278: OCTAVIO | J278: RAFAEL | K278: CAUSIL | L278: YANEZ
A279: 78703915 | B279: BRR CARTAGENITA | D279: Ciénaga De Oro | E279: 23 | F279: 189 | G279: 13 | I279: FREY | J279: RAUL | K279: MONTES | L279: DIAZ
A280: 78707110 | B280: BARR LOS NOGALES MANZANA H 2 | D280: Montería | E280: 23 | F280: 001 | G280: 13 | I280: NAVO | J280: NASAR | K280: VILLALBA | L280: BURGOS
A281: 78751172 | B281: CL 30 2 58 | D281: Montería | E281: 23 | F281: 001 | G281: 13 | I281: Alvaro | J281: Jose | K281: Soto | L281: Galvan
A282: 91277817 | B282: CL 51A 18 54 | D282: Bucaramanga | E282: 68 | F282: 001 | G282: 13 | I282: CARLOS | J282: YESID | K282: BARBOSA | L282: CARRENO
A283: 1003173154 | B283: CR 11 9 60 | D283: El Paso | E283: 20 | F283: 250 | G283: 13 | I283: PAULA | K283: OROZCO
A284: 1003205478 | B284: CR 57 G 26 P 2 | D284: Bogota D.C. | E284: 11 | F284: 001 | G284: 13 | I284: JADER | J284: DAVID | K284: PINEDA | L284: ROMERO
A285: 1003252643 | B285: CL 10 CR 10 A # 26 | D285: El Paso | E285: 20 | F285: 250 | G285: 13 | I285: CARLOS | J285: ALBERTO | K285: MAESTRE | L285: RESTREPO
A286: 1003432418 | B286: BRR EL CRUCE CORR LA LOMA | D286: El Paso | E286: 20 | F286: 250 | G286: 13 | I286: JUAN | J286: JOSE | K286: HEREDIA | L286: BLANCO
A287: 1003456962 | B287: CR 25 1A 23 | D287: Ciénaga De Oro | E287: 23 | F287: 189 | G287: 13 | I287: JESUS | J287: ANTONIO | K287: MARRUGO | L287: AVILEZ
A288: 1003459015 | B288: VDA BARRO BLANCO | D288: Rionegro | E288: 68 | F288: 615 | G288: 13 | I288: CARLOS | J288: MARIO | K288: ARGUMEDO | L288: FUENTES
A289: 1042849624 | B289: CL 16 14 A 30 | D289: Magangué | E289: 13 | F289: 430 | G289: 13 | I289: JASSON | J289: MIGUEL | K289: BEDOYA | L289: MARTINEZ
A290: 1064799980 | B290: BRR LA AURORA | D290: El Paso | E290: 20 | F290: 250 | G290: 13 | I290: MARIA | J290: CAROLINA | K290: TORRES | L290: DE ANGEL
A291: 1064976279 | B291: CL 6 N 12 06 | D291: Ciénaga De Oro | E291: 23 | F291: 189 | G291: 13 | I291: FRAY | K291: FUENTES | L291: CORBIS
A292: 1065997547 | B292: CL 12 # 7-50 BARRIO ALAMOS | D292: El Paso | E292: 20 | F292: 250 | G292: 13 | I292: OLIVER | J292: JOSE | K292: GUTIERREZ | L292: PARRA
A293: 1068583585 | B293: CR 18 WW 18 48 | D293: Montería | E293: 23 | F293: 001 | G293: 13 | I293: OSCAR | J293: IVAN | K293: DE ORO | L293: AGUADO
A294: 1068663459 | B294: CL 2 D 22 19 | D294: Ciénaga De Oro | E294: 23 | F294: 189 | G294: 13 | I294: LUIS | J294: CARLOS | K294: SERGE | L294: OVIEDO
A295: 1068667395 | B295: BRR SAN ISIDRO | D295: Montería | E295: 23 | F295: 001 | G295: 13 | I295: MARIA | J295: JOSE | K295: PASTRANA | L295: SALGADO
A296: 1073813047 | B296: BRR 13 MAYO | D296: Ciénaga De Oro | E296: 23 | F296: 189 | G296: 13 | I296: LEIBER | J296: DAVID | K296: ARRIETA | L296: TIRADO
A297: 1101818543 | B297: BRR ALAMOS NORTE | D297: El Paso | E297: 20 | F297: 250 | G297: 13 | I297: MICHEL | J297: CAROLINA | K297: CARO | L297: PEREZ
...
